[{"outline":[{"type":"M","x":407,"y":1462},{"type":"L","x":394,"y":703},{"type":"Q","begin":{"x":392,"y":599},"end":{"x":389.5,"y":576.5}},{"type":"Q","begin":{"x":387,"y":554},"end":{"x":375.5,"y":520.5}},{"type":"Q","begin":{"x":364,"y":487},"end":{"x":362.5,"y":478.5}},{"type":"Q","begin":{"x":361,"y":470},"end":{"x":365.5,"y":464}},{"type":"Q","begin":{"x":370,"y":458},"end":{"x":384,"y":456}},{"type":"Q","begin":{"x":398,"y":455},"end":{"x":440.5,"y":465}},{"type":"Q","begin":{"x":483,"y":475},"end":{"x":492,"y":483}},{"type":"L","x":516,"y":505},{"type":"L","x":510,"y":556},{"type":"L","x":503,"y":834},{"type":"L","x":503,"y":881},{"type":"L","x":500,"y":1109},{"type":"L","x":497,"y":1160},{"type":"L","x":492,"y":1443},{"type":"Q","begin":{"x":451.5,"y":1509.5},"end":{"x":407,"y":1462}}],"track":[{"x":430,"y":476,"size":95},{"x":461,"y":1495,"size":70}]},{"outline":[{"type":"M","x":492,"y":483},{"type":"L","x":516,"y":505},{"type":"L","x":728,"y":461},{"type":"Q","begin":{"x":739,"y":459},"end":{"x":761,"y":450}},{"type":"L","x":803,"y":433},{"type":"Q","begin":{"x":822,"y":425},"end":{"x":833,"y":424}},{"type":"Q","begin":{"x":854,"y":422},"end":{"x":898.5,"y":446}},{"type":"Q","begin":{"x":943,"y":470},"end":{"x":960,"y":481.5}},{"type":"Q","begin":{"x":977,"y":493},"end":{"x":983,"y":503}},{"type":"Q","begin":{"x":989,"y":513},"end":{"x":989,"y":522}},{"type":"Q","begin":{"x":988,"y":528},"end":{"x":976,"y":549.5}},{"type":"Q","begin":{"x":964,"y":571},"end":{"x":960.5,"y":604.5}},{"type":"Q","begin":{"x":957,"y":638},"end":{"x":951,"y":742}},{"type":"L","x":912,"y":1332},{"type":"Q","begin":{"x":882,"y":1412.5},"end":{"x":812,"y":1363}},{"type":"L","x":817,"y":1110},{"type":"L","x":817,"y":1067},{"type":"L","x":821,"y":835},{"type":"L","x":823,"y":800},{"type":"L","x":823,"y":606},{"type":"Q","begin":{"x":823,"y":546},"end":{"x":817.5,"y":533.5}},{"type":"Q","begin":{"x":812,"y":521},"end":{"x":801.5,"y":515.5}},{"type":"Q","begin":{"x":791,"y":510},"end":{"x":778,"y":510}},{"type":"L","x":697,"y":525},{"type":"L","x":510,"y":556},{"type":"Q","begin":{"x":520,"y":522.5},"end":{"x":492,"y":483}}],"track":[{"x":543,"y":516,"size":65},{"x":841,"y":438,"size":50},{"x":941,"y":499,"size":60},{"x":870,"y":1320,"size":75}]},{"outline":[{"type":"M","x":821,"y":835},{"type":"Q","begin":{"x":699,"y":865},"end":{"x":645,"y":879.5}},{"type":"Q","begin":{"x":591,"y":894},"end":{"x":564.5,"y":895.5}},{"type":"Q","begin":{"x":538,"y":897},"end":{"x":522,"y":889}},{"type":"L","x":503,"y":881},{"type":"L","x":503,"y":834},{"type":"Q","begin":{"x":519,"y":833},"end":{"x":538,"y":830}},{"type":"Q","begin":{"x":557,"y":827},"end":{"x":590.5,"y":817.5}},{"type":"Q","begin":{"x":624,"y":808},"end":{"x":656,"y":794.5}},{"type":"Q","begin":{"x":688,"y":781},"end":{"x":703,"y":777.5}},{"type":"Q","begin":{"x":718,"y":774},"end":{"x":736,"y":776}},{"type":"Q","begin":{"x":745,"y":778},"end":{"x":769,"y":784}},{"type":"L","x":823,"y":800},{"type":"L","x":821,"y":835}],"track":[{"x":513,"y":853},{"x":800,"y":816}]},{"outline":[{"type":"M","x":817,"y":1110},{"type":"Q","begin":{"x":788,"y":1117},"end":{"x":775,"y":1120}},{"type":"L","x":661,"y":1148},{"type":"Q","begin":{"x":619,"y":1158},"end":{"x":581.5,"y":1163}},{"type":"Q","begin":{"x":544,"y":1168},"end":{"x":533,"y":1165}},{"type":"L","x":497,"y":1160},{"type":"L","x":500,"y":1109},{"type":"Q","begin":{"x":518,"y":1109},"end":{"x":536.5,"y":1106.5}},{"type":"Q","begin":{"x":555,"y":1104},"end":{"x":603.5,"y":1088.5}},{"type":"Q","begin":{"x":652,"y":1073},"end":{"x":680.5,"y":1059.5}},{"type":"Q","begin":{"x":709,"y":1046},"end":{"x":722,"y":1045}},{"type":"Q","begin":{"x":730,"y":1045},"end":{"x":756,"y":1051}},{"type":"L","x":817,"y":1067},{"type":"L","x":817,"y":1110}],"track":[{"x":510,"y":1146},{"x":803,"y":1090}]},{"outline":[{"type":"M","x":912,"y":1332},{"type":"L","x":1015,"y":1307},{"type":"Q","begin":{"x":1068,"y":1295},"end":{"x":1080.5,"y":1303.5}},{"type":"Q","begin":{"x":1093,"y":1312},"end":{"x":1095.5,"y":1326}},{"type":"Q","begin":{"x":1098,"y":1340},"end":{"x":1075,"y":1348}},{"type":"L","x":1042,"y":1360},{"type":"Q","begin":{"x":976,"y":1384},"end":{"x":916.5,"y":1405}},{"type":"Q","begin":{"x":857,"y":1426},"end":{"x":711.5,"y":1474}},{"type":"Q","begin":{"x":566,"y":1522},"end":{"x":516,"y":1543}},{"type":"Q","begin":{"x":466,"y":1564},"end":{"x":433,"y":1582}},{"type":"L","x":377,"y":1612},{"type":"Q","begin":{"x":350,"y":1626},"end":{"x":328.5,"y":1626.5}},{"type":"Q","begin":{"x":307,"y":1627},"end":{"x":272,"y":1601}},{"type":"Q","begin":{"x":246,"y":1584},"end":{"x":216,"y":1553.5}},{"type":"Q","begin":{"x":186,"y":1523},"end":{"x":178,"y":1509.5}},{"type":"Q","begin":{"x":170,"y":1496},"end":{"x":172,"y":1485.5}},{"type":"Q","begin":{"x":174,"y":1475},"end":{"x":182.5,"y":1470.5}},{"type":"Q","begin":{"x":191,"y":1466},"end":{"x":216,"y":1469}},{"type":"L","x":268,"y":1470},{"type":"L","x":327,"y":1474},{"type":"L","x":407,"y":1462},{"type":"L","x":492,"y":1443},{"type":"L","x":812,"y":1363},{"type":"L","x":912,"y":1332}],"track":[{"x":260,"y":1576},{"x":1066,"y":1326}]},{"outline":[{"type":"M","x":1317,"y":833},{"type":"L","x":1285,"y":840},{"type":"Q","begin":{"x":1273,"y":843},"end":{"x":1243,"y":853.5}},{"type":"Q","begin":{"x":1213,"y":864},"end":{"x":1199,"y":870.5}},{"type":"Q","begin":{"x":1185,"y":877},"end":{"x":1178,"y":877}},{"type":"Q","begin":{"x":1165,"y":879},"end":{"x":1142,"y":871}},{"type":"Q","begin":{"x":1119,"y":863},"end":{"x":1103,"y":853}},{"type":"L","x":1070,"y":831},{"type":"Q","begin":{"x":1059,"y":825},"end":{"x":1052,"y":816}},{"type":"Q","begin":{"x":1045,"y":807},"end":{"x":1049.5,"y":800}},{"type":"Q","begin":{"x":1054,"y":793},"end":{"x":1068,"y":792}},{"type":"L","x":1123,"y":789},{"type":"Q","begin":{"x":1150,"y":788},"end":{"x":1189,"y":784}},{"type":"Q","begin":{"x":1228,"y":780},"end":{"x":1260,"y":774}},{"type":"L","x":1333,"y":761},{"type":"L","x":1454,"y":739},{"type":"L","x":1582,"y":717},{"type":"Q","begin":{"x":1585,"y":717},"end":{"x":1628,"y":704.5}},{"type":"Q","begin":{"x":1671,"y":692},"end":{"x":1689.5,"y":684.5}},{"type":"Q","begin":{"x":1708,"y":677},"end":{"x":1712,"y":676}},{"type":"Q","begin":{"x":1732,"y":673},"end":{"x":1753.5,"y":684}},{"type":"Q","begin":{"x":1775,"y":695},"end":{"x":1809.5,"y":719.5}},{"type":"Q","begin":{"x":1844,"y":744},"end":{"x":1859,"y":760}},{"type":"Q","begin":{"x":1874,"y":776},"end":{"x":1875.5,"y":790}},{"type":"Q","begin":{"x":1877,"y":804},"end":{"x":1869,"y":821}},{"type":"L","x":1843,"y":866},{"type":"Q","begin":{"x":1830,"y":890},"end":{"x":1826.5,"y":905.5}},{"type":"Q","begin":{"x":1823,"y":921},"end":{"x":1814,"y":988}},{"type":"L","x":1759,"y":1371},{"type":"Q","begin":{"x":1733,"y":1550},"end":{"x":1693.5,"y":1618}},{"type":"Q","begin":{"x":1654,"y":1686},"end":{"x":1631,"y":1713.5}},{"type":"Q","begin":{"x":1608,"y":1741},"end":{"x":1568,"y":1766}},{"type":"Q","begin":{"x":1528,"y":1791},"end":{"x":1504,"y":1779}},{"type":"Q","begin":{"x":1489,"y":1773},"end":{"x":1473,"y":1743}},{"type":"L","x":1451,"y":1703},{"type":"Q","begin":{"x":1436,"y":1680},"end":{"x":1409,"y":1648}},{"type":"L","x":1362,"y":1597},{"type":"Q","begin":{"x":1340,"y":1573},"end":{"x":1331,"y":1565}},{"type":"L","x":1315,"y":1552},{"type":"Q","begin":{"x":1303,"y":1543},"end":{"x":1308,"y":1536}},{"type":"Q","begin":{"x":1313,"y":1529},"end":{"x":1324,"y":1532}},{"type":"L","x":1356,"y":1543},{"type":"L","x":1396,"y":1557},{"type":"Q","begin":{"x":1418,"y":1565},"end":{"x":1455,"y":1574.5}},{"type":"Q","begin":{"x":1492,"y":1584},"end":{"x":1511,"y":1580}},{"type":"Q","begin":{"x":1541,"y":1575},"end":{"x":1557,"y":1553}},{"type":"Q","begin":{"x":1573,"y":1531},"end":{"x":1591,"y":1473.5}},{"type":"Q","begin":{"x":1609,"y":1416},"end":{"x":1624.5,"y":1346}},{"type":"Q","begin":{"x":1640,"y":1276},"end":{"x":1653,"y":1189}},{"type":"Q","begin":{"x":1666,"y":1102},"end":{"x":1676,"y":1025}},{"type":"Q","begin":{"x":1686,"y":948},"end":{"x":1690,"y":899.5}},{"type":"Q","begin":{"x":1694,"y":851},"end":{"x":1689.5,"y":826.5}},{"type":"Q","begin":{"x":1685,"y":802},"end":{"x":1674,"y":792.5}},{"type":"Q","begin":{"x":1663,"y":783},"end":{"x":1622,"y":785}},{"type":"Q","begin":{"x":1581,"y":787},"end":{"x":1555,"y":789}},{"type":"L","x":1440,"y":802},{"type":"L","x":1317,"y":833}],"track":[{"x":1113,"y":836,"size":80},{"x":1516,"y":763,"size":55},{"x":1731,"y":707,"size":70},{"x":1821,"y":798,"size":140},{"x":1746,"y":1146,"size":115},{"x":1550,"y":1761,"size":105},{"x":1323,"y":1545,"size":85}]},{"outline":[{"type":"M","x":1440,"y":802},{"type":"Q","begin":{"x":1414,"y":896},"end":{"x":1393.5,"y":967.5}},{"type":"Q","begin":{"x":1373,"y":1039},"end":{"x":1340.5,"y":1132.5}},{"type":"Q","begin":{"x":1308,"y":1226},"end":{"x":1268.5,"y":1308.5}},{"type":"Q","begin":{"x":1229,"y":1391},"end":{"x":1170.5,"y":1482}},{"type":"Q","begin":{"x":1112,"y":1573},"end":{"x":1041,"y":1656.5}},{"type":"Q","begin":{"x":970,"y":1740},"end":{"x":929.5,"y":1770.5}},{"type":"Q","begin":{"x":889,"y":1801},"end":{"x":861,"y":1812}},{"type":"L","x":842,"y":1820},{"type":"Q","begin":{"x":820,"y":1830},"end":{"x":817.5,"y":1822.5}},{"type":"Q","begin":{"x":815,"y":1815},"end":{"x":825,"y":1803}},{"type":"L","x":847,"y":1776},{"type":"Q","begin":{"x":879,"y":1736},"end":{"x":908.5,"y":1699.5}},{"type":"Q","begin":{"x":938,"y":1663},"end":{"x":983.5,"y":1596}},{"type":"Q","begin":{"x":1029,"y":1529},"end":{"x":1082,"y":1435}},{"type":"Q","begin":{"x":1135,"y":1341},"end":{"x":1171,"y":1262.5}},{"type":"Q","begin":{"x":1207,"y":1184},"end":{"x":1240,"y":1095}},{"type":"Q","begin":{"x":1273,"y":1006},"end":{"x":1292,"y":931}},{"type":"L","x":1317,"y":833},{"type":"L","x":1333,"y":761},{"type":"Q","begin":{"x":1346,"y":704},"end":{"x":1353,"y":669}},{"type":"Q","begin":{"x":1360,"y":634},"end":{"x":1374,"y":549.5}},{"type":"Q","begin":{"x":1388,"y":465},"end":{"x":1391,"y":428.5}},{"type":"Q","begin":{"x":1394,"y":392},"end":{"x":1394.5,"y":352.5}},{"type":"Q","begin":{"x":1395,"y":313},"end":{"x":1387,"y":289}},{"type":"Q","begin":{"x":1385,"y":286},"end":{"x":1378,"y":268.5}},{"type":"Q","begin":{"x":1371,"y":251},"end":{"x":1374,"y":243}},{"type":"Q","begin":{"x":1377,"y":235},"end":{"x":1385,"y":231.5}},{"type":"Q","begin":{"x":1393,"y":228},"end":{"x":1406,"y":228}},{"type":"Q","begin":{"x":1422,"y":229},"end":{"x":1440,"y":234}},{"type":"Q","begin":{"x":1458,"y":239},"end":{"x":1482,"y":250.5}},{"type":"Q","begin":{"x":1506,"y":262},"end":{"x":1522,"y":273.5}},{"type":"Q","begin":{"x":1538,"y":285},"end":{"x":1553,"y":302.5}},{"type":"Q","begin":{"x":1568,"y":320},"end":{"x":1566,"y":331}},{"type":"Q","begin":{"x":1565,"y":334},"end":{"x":1557.5,"y":345.5}},{"type":"Q","begin":{"x":1550,"y":357},"end":{"x":1538.5,"y":392}},{"type":"Q","begin":{"x":1527,"y":427},"end":{"x":1525,"y":433.5}},{"type":"Q","begin":{"x":1523,"y":440},"end":{"x":1512,"y":490.5}},{"type":"Q","begin":{"x":1501,"y":541},"end":{"x":1482,"y":621}},{"type":"L","x":1463,"y":702},{"type":"L","x":1454,"y":739},{"type":"L","x":1440,"y":802}],"track":[{"x":1490,"y":285},{"x":1405,"y":665},{"x":1365,"y":920},{"x":1195,"y":1385},{"x":875,"y":1790}]}]