[{"outline":[{"type":"M","x":441,"y":1693},{"type":"L","x":436,"y":1740},{"type":"Q","begin":{"x":432,"y":1776},"end":{"x":425,"y":1790}},{"type":"Q","begin":{"x":418,"y":1804},"end":{"x":407,"y":1804.5}},{"type":"Q","begin":{"x":396,"y":1805},"end":{"x":386,"y":1796}},{"type":"Q","begin":{"x":372,"y":1786},"end":{"x":358.5,"y":1762.5}},{"type":"Q","begin":{"x":345,"y":1739},"end":{"x":335.5,"y":1705.5}},{"type":"Q","begin":{"x":326,"y":1672},"end":{"x":325,"y":1644}},{"type":"Q","begin":{"x":324,"y":1616},"end":{"x":330,"y":1571}},{"type":"L","x":350,"y":1446},{"type":"Q","begin":{"x":358,"y":1391},"end":{"x":364.5,"y":1313.5}},{"type":"Q","begin":{"x":371,"y":1236},"end":{"x":377,"y":1098}},{"type":"L","x":386,"y":854},{"type":"Q","begin":{"x":391,"y":716},"end":{"x":391.5,"y":674.5}},{"type":"Q","begin":{"x":392,"y":633},"end":{"x":389,"y":542}},{"type":"Q","begin":{"x":386,"y":477},"end":{"x":383,"y":445}},{"type":"Q","begin":{"x":380,"y":413},"end":{"x":374,"y":380.5}},{"type":"Q","begin":{"x":368,"y":348},"end":{"x":359.5,"y":326}},{"type":"Q","begin":{"x":351,"y":304},"end":{"x":348.5,"y":292.5}},{"type":"Q","begin":{"x":346,"y":281},"end":{"x":351,"y":275.5}},{"type":"Q","begin":{"x":356,"y":270},"end":{"x":377,"y":272}},{"type":"Q","begin":{"x":403,"y":275},"end":{"x":414,"y":277.5}},{"type":"Q","begin":{"x":425,"y":280},"end":{"x":447,"y":286}},{"type":"L","x":473,"y":294},{"type":"Q","begin":{"x":506.5,"y":305},"end":{"x":486,"y":370}},{"type":"Q","begin":{"x":486,"y":437},"end":{"x":485.5,"y":504.5}},{"type":"Q","begin":{"x":485,"y":572},"end":{"x":484,"y":648}},{"type":"L","x":480,"y":787},{"type":"L","x":478,"y":862},{"type":"L","x":478,"y":884},{"type":"Q","begin":{"x":474,"y":1009},"end":{"x":472,"y":1081}},{"type":"Q","begin":{"x":470,"y":1153},"end":{"x":466.5,"y":1241}},{"type":"Q","begin":{"x":463,"y":1329},"end":{"x":460.5,"y":1383.5}},{"type":"Q","begin":{"x":458,"y":1438},"end":{"x":453,"y":1527}},{"type":"L","x":447,"y":1626},{"type":"L","x":441,"y":1693}],"track":[{"x":415,"y":285},{"x":398,"y":1739}]},{"outline":[{"type":"M","x":473,"y":294},{"type":"Q","begin":{"x":533,"y":291},"end":{"x":581.5,"y":288}},{"type":"Q","begin":{"x":630,"y":285},"end":{"x":766,"y":273}},{"type":"Q","begin":{"x":902,"y":261},"end":{"x":929,"y":258}},{"type":"L","x":1090,"y":245},{"type":"Q","begin":{"x":1188,"y":237},"end":{"x":1278,"y":226}},{"type":"Q","begin":{"x":1368,"y":215},"end":{"x":1411.5,"y":207.5}},{"type":"Q","begin":{"x":1455,"y":200},"end":{"x":1486,"y":193}},{"type":"Q","begin":{"x":1517,"y":186},"end":{"x":1529,"y":186}},{"type":"Q","begin":{"x":1540,"y":187},"end":{"x":1560.5,"y":193}},{"type":"Q","begin":{"x":1581,"y":199},"end":{"x":1601,"y":207.5}},{"type":"Q","begin":{"x":1621,"y":216},"end":{"x":1650.5,"y":234.5}},{"type":"Q","begin":{"x":1680,"y":253},"end":{"x":1700.5,"y":270.5}},{"type":"Q","begin":{"x":1721,"y":288},"end":{"x":1721.5,"y":299}},{"type":"Q","begin":{"x":1722,"y":310},"end":{"x":1713,"y":328}},{"type":"Q","begin":{"x":1704,"y":346},"end":{"x":1695,"y":374.5}},{"type":"Q","begin":{"x":1686,"y":403},"end":{"x":1681,"y":434.5}},{"type":"Q","begin":{"x":1676,"y":466},"end":{"x":1674,"y":519}},{"type":"Q","begin":{"x":1672,"y":572},"end":{"x":1670,"y":662}},{"type":"Q","begin":{"x":1668,"y":752},"end":{"x":1669,"y":812}},{"type":"L","x":1674,"y":1115},{"type":"Q","begin":{"x":1675,"y":1220},"end":{"x":1677,"y":1266}},{"type":"L","x":1682,"y":1429},{"type":"L","x":1685,"y":1574},{"type":"Q","begin":{"x":1686,"y":1643},"end":{"x":1685,"y":1671}},{"type":"Q","begin":{"x":1682,"y":1710},"end":{"x":1673.5,"y":1738}},{"type":"Q","begin":{"x":1665,"y":1766},"end":{"x":1644,"y":1801.5}},{"type":"Q","begin":{"x":1623,"y":1837},"end":{"x":1601.5,"y":1851.5}},{"type":"Q","begin":{"x":1580,"y":1866},"end":{"x":1569,"y":1863}},{"type":"Q","begin":{"x":1557,"y":1861},"end":{"x":1544,"y":1838.5}},{"type":"Q","begin":{"x":1531,"y":1816},"end":{"x":1509.5,"y":1768}},{"type":"Q","begin":{"x":1488,"y":1720},"end":{"x":1477,"y":1698}},{"type":"L","x":1452,"y":1649},{"type":"Q","begin":{"x":1403.25,"y":1528.25},"end":{"x":1508.5,"y":1599.5}},{"type":"Q","begin":{"x":1526,"y":1611},"end":{"x":1532,"y":1609}},{"type":"Q","begin":{"x":1540,"y":1607},"end":{"x":1543.5,"y":1577}},{"type":"Q","begin":{"x":1547,"y":1547},"end":{"x":1548,"y":1510.5}},{"type":"Q","begin":{"x":1549,"y":1474},"end":{"x":1553,"y":1367}},{"type":"Q","begin":{"x":1557,"y":1260},"end":{"x":1558.5,"y":1195.5}},{"type":"Q","begin":{"x":1560,"y":1131},"end":{"x":1560,"y":1035}},{"type":"Q","begin":{"x":1559,"y":948},"end":{"x":1558,"y":874.5}},{"type":"Q","begin":{"x":1557,"y":801},"end":{"x":1554,"y":711}},{"type":"Q","begin":{"x":1551,"y":621},"end":{"x":1548,"y":546}},{"type":"Q","begin":{"x":1545,"y":471},"end":{"x":1540.5,"y":423.5}},{"type":"Q","begin":{"x":1536,"y":376},"end":{"x":1530,"y":345.5}},{"type":"Q","begin":{"x":1524,"y":315},"end":{"x":1514.5,"y":305}},{"type":"Q","begin":{"x":1505,"y":295},"end":{"x":1478.5,"y":291}},{"type":"Q","begin":{"x":1452,"y":287},"end":{"x":1399,"y":290}},{"type":"L","x":1254,"y":297},{"type":"Q","begin":{"x":1212,"y":300},"end":{"x":1136.5,"y":306.5}},{"type":"Q","begin":{"x":1061,"y":313},"end":{"x":955.5,"y":322}},{"type":"Q","begin":{"x":850,"y":331},"end":{"x":783,"y":338}},{"type":"Q","begin":{"x":716,"y":345},"end":{"x":643.5,"y":357}},{"type":"Q","begin":{"x":571,"y":369},"end":{"x":549,"y":372}},{"type":"Q","begin":{"x":527,"y":375},"end":{"x":517,"y":373}},{"type":"L","x":486,"y":370},{"type":"L","x":473,"y":294}],"track":[{"x":490,"y":325},{"x":1541,"y":216,"size":175},{"x":1683,"y":300,"size":175},{"x":1605,"y":396,"size":160},{"x":1646,"y":1510},{"x":1603,"y":1900},{"x":1460,"y":1626}]},{"outline":[{"type":"M","x":814,"y":695},{"type":"Q","begin":{"x":812,"y":708},"end":{"x":806.5,"y":716}},{"type":"Q","begin":{"x":801,"y":724},"end":{"x":789,"y":723}},{"type":"Q","begin":{"x":778,"y":723},"end":{"x":768.5,"y":712}},{"type":"Q","begin":{"x":759,"y":701},"end":{"x":750.5,"y":670}},{"type":"Q","begin":{"x":742,"y":639},"end":{"x":736,"y":602}},{"type":"Q","begin":{"x":730,"y":565},"end":{"x":726.5,"y":550}},{"type":"Q","begin":{"x":723,"y":535},"end":{"x":715,"y":518}},{"type":"Q","begin":{"x":707,"y":501},"end":{"x":701,"y":492}},{"type":"L","x":676,"y":464},{"type":"Q","begin":{"x":666,"y":451},"end":{"x":669,"y":446}},{"type":"Q","begin":{"x":672,"y":441},"end":{"x":684,"y":439}},{"type":"Q","begin":{"x":694,"y":438},"end":{"x":720,"y":442}},{"type":"L","x":750,"y":447},{"type":"L","x":773,"y":453},{"type":"Q","begin":{"x":808.5,"y":459},"end":{"x":798,"y":505}},{"type":"Q","begin":{"x":804,"y":555},"end":{"x":806,"y":564}},{"type":"L","x":817,"y":631},{"type":"L","x":814,"y":695}],"track":[{"x":710,"y":453},{"x":783,"y":710}]},{"outline":[{"type":"M","x":773,"y":453},{"type":"Q","begin":{"x":825,"y":445},"end":{"x":851,"y":440}},{"type":"L","x":942,"y":422},{"type":"Q","begin":{"x":969,"y":417},"end":{"x":1026.5,"y":407.5}},{"type":"Q","begin":{"x":1084,"y":398},"end":{"x":1111.5,"y":391.5}},{"type":"Q","begin":{"x":1139,"y":385},"end":{"x":1151,"y":384}},{"type":"Q","begin":{"x":1165,"y":384},"end":{"x":1188,"y":391.5}},{"type":"Q","begin":{"x":1211,"y":399},"end":{"x":1228.5,"y":410.5}},{"type":"Q","begin":{"x":1246,"y":422},"end":{"x":1261,"y":434.5}},{"type":"Q","begin":{"x":1276,"y":447},"end":{"x":1285.5,"y":458}},{"type":"Q","begin":{"x":1295,"y":469},"end":{"x":1293,"y":478}},{"type":"Q","begin":{"x":1291,"y":485},"end":{"x":1279,"y":495}},{"type":"L","x":1254,"y":515},{"type":"Q","begin":{"x":1239,"y":528},"end":{"x":1220.5,"y":550}},{"type":"Q","begin":{"x":1202,"y":572},"end":{"x":1196,"y":584}},{"type":"L","x":1176,"y":620},{"type":"Q","begin":{"x":1088.5,"y":666.5},"end":{"x":1093,"y":601}},{"type":"Q","begin":{"x":1098,"y":575},"end":{"x":1100,"y":565.5}},{"type":"Q","begin":{"x":1102,"y":556},"end":{"x":1107.5,"y":531.5}},{"type":"Q","begin":{"x":1113,"y":507},"end":{"x":1115,"y":492}},{"type":"Q","begin":{"x":1117,"y":477},"end":{"x":1111.5,"y":469}},{"type":"Q","begin":{"x":1106,"y":461},"end":{"x":1083.5,"y":461.5}},{"type":"Q","begin":{"x":1061,"y":462},"end":{"x":1015,"y":470}},{"type":"L","x":923,"y":484},{"type":"L","x":831,"y":500},{"type":"L","x":798,"y":505},{"type":"L","x":773,"y":453}],"track":[{"x":796,"y":483,"size":95},{"x":1152,"y":369,"size":105},{"x":1242,"y":433,"size":95},{"x":1130,"y":650,"size":90}]},{"outline":[{"type":"M","x":920,"y":686},{"type":"Q","begin":{"x":896,"y":691},"end":{"x":877.5,"y":693.5}},{"type":"Q","begin":{"x":859,"y":696},"end":{"x":845,"y":695}},{"type":"L","x":814,"y":695},{"type":"L","x":817,"y":631},{"type":"Q","begin":{"x":856,"y":630},"end":{"x":883,"y":628}},{"type":"Q","begin":{"x":910,"y":626},"end":{"x":953,"y":620}},{"type":"L","x":1032,"y":609},{"type":"L","x":1093,"y":601},{"type":"L","x":1176,"y":620},{"type":"Q","begin":{"x":1188,"y":630},"end":{"x":1198.5,"y":640.5}},{"type":"Q","begin":{"x":1209,"y":651},"end":{"x":1206.5,"y":657}},{"type":"Q","begin":{"x":1204,"y":663},"end":{"x":1185,"y":665}},{"type":"L","x":1134,"y":667},{"type":"L","x":1065,"y":674},{"type":"L","x":1004,"y":678},{"type":"L","x":920,"y":686}],"track":[{"x":813,"y":656},{"x":1200,"y":643}]},{"outline":[{"type":"M","x":923,"y":814},{"type":"Q","begin":{"x":924,"y":793},"end":{"x":925,"y":768}},{"type":"Q","begin":{"x":926,"y":743},"end":{"x":925,"y":729}},{"type":"L","x":920,"y":686},{"type":"L","x":1004,"y":678},{"type":"Q","begin":{"x":1012,"y":685},"end":{"x":1022.5,"y":695.5}},{"type":"Q","begin":{"x":1033,"y":706},"end":{"x":1031.5,"y":716.5}},{"type":"Q","begin":{"x":1030,"y":727},"end":{"x":1016.5,"y":744.5}},{"type":"Q","begin":{"x":1003,"y":762},"end":{"x":1000,"y":773}},{"type":"L","x":989,"y":806},{"type":"Q","begin":{"x":916,"y":884},"end":{"x":923,"y":814}}],"track":[{"x":970,"y":683},{"x":963,"y":800}]},{"outline":[{"type":"M","x":478,"y":862},{"type":"Q","begin":{"x":511,"y":861},"end":{"x":537.5,"y":859}},{"type":"Q","begin":{"x":564,"y":857},"end":{"x":614,"y":851}},{"type":"L","x":736,"y":837},{"type":"Q","begin":{"x":855,"y":825},"end":{"x":862,"y":823}},{"type":"L","x":923,"y":814},{"type":"L","x":989,"y":806},{"type":"Q","begin":{"x":1031,"y":801},"end":{"x":1053,"y":798}},{"type":"L","x":1151,"y":787},{"type":"Q","begin":{"x":1171,"y":785},"end":{"x":1246.5,"y":773.5}},{"type":"Q","begin":{"x":1322,"y":762},"end":{"x":1344.5,"y":758}},{"type":"Q","begin":{"x":1367,"y":754},"end":{"x":1382,"y":754}},{"type":"Q","begin":{"x":1400,"y":755},"end":{"x":1412,"y":760}},{"type":"Q","begin":{"x":1424,"y":765},"end":{"x":1454.5,"y":784.5}},{"type":"Q","begin":{"x":1485,"y":804},"end":{"x":1490,"y":814.5}},{"type":"Q","begin":{"x":1495,"y":825},"end":{"x":1491.5,"y":834}},{"type":"Q","begin":{"x":1488,"y":843},"end":{"x":1469,"y":843}},{"type":"L","x":1401,"y":845},{"type":"Q","begin":{"x":1357,"y":847},"end":{"x":1316,"y":849}},{"type":"L","x":1209,"y":857},{"type":"L","x":1079,"y":865},{"type":"Q","begin":{"x":1016,"y":870},"end":{"x":937,"y":879}},{"type":"L","x":798,"y":896},{"type":"Q","begin":{"x":712,"y":906},"end":{"x":666,"y":915.5}},{"type":"Q","begin":{"x":620,"y":925},"end":{"x":603,"y":924}},{"type":"Q","begin":{"x":583,"y":924},"end":{"x":554.5,"y":917.5}},{"type":"Q","begin":{"x":526,"y":911},"end":{"x":512,"y":902}},{"type":"L","x":478,"y":884},{"type":"L","x":478,"y":862}],"track":[{"x":540,"y":896},{"x":1438,"y":810}]},{"outline":[{"type":"M","x":764,"y":1474},{"type":"Q","begin":{"x":762,"y":1496},"end":{"x":757,"y":1511.5}},{"type":"Q","begin":{"x":752,"y":1527},"end":{"x":741.5,"y":1529.5}},{"type":"Q","begin":{"x":731,"y":1532},"end":{"x":720,"y":1522}},{"type":"Q","begin":{"x":708,"y":1513},"end":{"x":699,"y":1479}},{"type":"Q","begin":{"x":690,"y":1445},"end":{"x":687.5,"y":1430}},{"type":"Q","begin":{"x":685,"y":1415},"end":{"x":682,"y":1370.5}},{"type":"Q","begin":{"x":679,"y":1326},"end":{"x":670,"y":1245}},{"type":"L","x":659,"y":1149},{"type":"Q","begin":{"x":653,"y":1110},"end":{"x":647,"y":1085}},{"type":"Q","begin":{"x":641,"y":1060},"end":{"x":628,"y":1035}},{"type":"Q","begin":{"x":615,"y":1010},"end":{"x":613,"y":1001.5}},{"type":"Q","begin":{"x":611,"y":993},"end":{"x":614.5,"y":987}},{"type":"Q","begin":{"x":618,"y":981},"end":{"x":639,"y":982}},{"type":"Q","begin":{"x":655,"y":983},"end":{"x":673,"y":988.5}},{"type":"Q","begin":{"x":691,"y":994},"end":{"x":704,"y":999}},{"type":"L","x":720,"y":1006},{"type":"Q","begin":{"x":744.5,"y":1015.5},"end":{"x":729,"y":1045}},{"type":"Q","begin":{"x":734,"y":1079},"end":{"x":736,"y":1100.5}},{"type":"Q","begin":{"x":738,"y":1122},"end":{"x":742.5,"y":1189.5}},{"type":"Q","begin":{"x":747,"y":1257},"end":{"x":753,"y":1321}},{"type":"L","x":761,"y":1416},{"type":"L","x":764,"y":1474}],"track":[{"x":656,"y":990},{"x":736,"y":1520}]},{"outline":[{"type":"M","x":720,"y":1006},{"type":"Q","begin":{"x":760,"y":1001},"end":{"x":781,"y":998}},{"type":"L","x":878,"y":987},{"type":"Q","begin":{"x":925,"y":982},"end":{"x":973,"y":974.5}},{"type":"Q","begin":{"x":1021,"y":967},"end":{"x":1061,"y":959.5}},{"type":"Q","begin":{"x":1101,"y":952},"end":{"x":1137,"y":944}},{"type":"Q","begin":{"x":1173,"y":936},"end":{"x":1202,"y":926}},{"type":"Q","begin":{"x":1231,"y":916},"end":{"x":1243,"y":915}},{"type":"Q","begin":{"x":1254,"y":915},"end":{"x":1283.5,"y":923.5}},{"type":"Q","begin":{"x":1313,"y":932},"end":{"x":1330,"y":939.5}},{"type":"Q","begin":{"x":1347,"y":947},"end":{"x":1378.5,"y":963}},{"type":"Q","begin":{"x":1410,"y":979},"end":{"x":1421.5,"y":991.5}},{"type":"Q","begin":{"x":1433,"y":1004},"end":{"x":1432,"y":1015}},{"type":"Q","begin":{"x":1431,"y":1022},"end":{"x":1419,"y":1037}},{"type":"Q","begin":{"x":1407,"y":1052},"end":{"x":1398,"y":1071.5}},{"type":"Q","begin":{"x":1389,"y":1091},"end":{"x":1380.5,"y":1122.5}},{"type":"Q","begin":{"x":1372,"y":1154},"end":{"x":1353.5,"y":1224.5}},{"type":"Q","begin":{"x":1335,"y":1295},"end":{"x":1321.5,"y":1351}},{"type":"Q","begin":{"x":1308,"y":1407},"end":{"x":1298.5,"y":1436.5}},{"type":"Q","begin":{"x":1289,"y":1466},"end":{"x":1271,"y":1484}},{"type":"Q","begin":{"x":1253,"y":1502},"end":{"x":1237,"y":1499}},{"type":"Q","begin":{"x":1216,"y":1497},"end":{"x":1207,"y":1477}},{"type":"L","x":1187,"y":1443},{"type":"Q","begin":{"x":1143.5,"y":1374.5},"end":{"x":1196,"y":1386}},{"type":"Q","begin":{"x":1206,"y":1384},"end":{"x":1213,"y":1346}},{"type":"L","x":1229,"y":1257},{"type":"Q","begin":{"x":1240,"y":1195},"end":{"x":1246.5,"y":1125}},{"type":"Q","begin":{"x":1253,"y":1055},"end":{"x":1255.5,"y":1037}},{"type":"Q","begin":{"x":1258,"y":1019},"end":{"x":1250.5,"y":1009.5}},{"type":"Q","begin":{"x":1243,"y":1000},"end":{"x":1218,"y":998}},{"type":"Q","begin":{"x":1204,"y":998},"end":{"x":1173,"y":1002}},{"type":"L","x":1087,"y":1012},{"type":"L","x":996,"y":1024},{"type":"Q","begin":{"x":976,"y":1027},"end":{"x":922,"y":1031.5}},{"type":"Q","begin":{"x":868,"y":1036},"end":{"x":826,"y":1041}},{"type":"Q","begin":{"x":784,"y":1046},"end":{"x":776,"y":1045}},{"type":"L","x":729,"y":1045},{"type":"L","x":720,"y":1006}],"track":[{"x":736,"y":1026,"size":100},{"x":1281,"y":896,"size":105},{"x":1434,"y":967,"size":100},{"x":1344,"y":1086,"size":95},{"x":1246,"y":1470,"size":110}]},{"outline":[{"type":"M","x":906,"y":1310},{"type":"Q","begin":{"x":905,"y":1320},"end":{"x":902,"y":1330}},{"type":"Q","begin":{"x":899,"y":1340},"end":{"x":888.5,"y":1341.5}},{"type":"Q","begin":{"x":878,"y":1343},"end":{"x":868,"y":1329}},{"type":"Q","begin":{"x":859,"y":1319},"end":{"x":856,"y":1289}},{"type":"Q","begin":{"x":853,"y":1259},"end":{"x":849,"y":1235.5}},{"type":"Q","begin":{"x":845,"y":1212},"end":{"x":837.5,"y":1192}},{"type":"Q","begin":{"x":830,"y":1172},"end":{"x":820,"y":1156.5}},{"type":"Q","begin":{"x":810,"y":1141},"end":{"x":805.5,"y":1132.5}},{"type":"Q","begin":{"x":801,"y":1124},"end":{"x":805,"y":1119.5}},{"type":"Q","begin":{"x":809,"y":1115},"end":{"x":826,"y":1116}},{"type":"Q","begin":{"x":851,"y":1119},"end":{"x":857,"y":1121}},{"type":"L","x":881,"y":1129},{"type":"Q","begin":{"x":905,"y":1135.5},"end":{"x":889,"y":1168}},{"type":"L","x":895,"y":1215},{"type":"L","x":901,"y":1262},{"type":"L","x":906,"y":1310}],"track":[{"x":853,"y":1126},{"x":883,"y":1313}]},{"outline":[{"type":"M","x":881,"y":1129},{"type":"Q","begin":{"x":905,"y":1126},"end":{"x":929,"y":1121.5}},{"type":"Q","begin":{"x":953,"y":1117},"end":{"x":975,"y":1109}},{"type":"Q","begin":{"x":997,"y":1101},"end":{"x":1016,"y":1091}},{"type":"Q","begin":{"x":1035,"y":1081},"end":{"x":1043,"y":1079}},{"type":"Q","begin":{"x":1054,"y":1077},"end":{"x":1072,"y":1082}},{"type":"Q","begin":{"x":1090,"y":1087},"end":{"x":1110.5,"y":1096}},{"type":"Q","begin":{"x":1131,"y":1105},"end":{"x":1139,"y":1113}},{"type":"Q","begin":{"x":1147,"y":1121},"end":{"x":1147.5,"y":1127.5}},{"type":"Q","begin":{"x":1148,"y":1134},"end":{"x":1143,"y":1143}},{"type":"L","x":1129,"y":1163},{"type":"Q","begin":{"x":1124,"y":1170},"end":{"x":1111.5,"y":1191.5}},{"type":"Q","begin":{"x":1099,"y":1213},"end":{"x":1098,"y":1218}},{"type":"L","x":1085,"y":1254},{"type":"Q","begin":{"x":1015.5,"y":1287.5},"end":{"x":1026,"y":1241}},{"type":"L","x":1037,"y":1182},{"type":"Q","begin":{"x":1040,"y":1166},"end":{"x":1039.5,"y":1157}},{"type":"Q","begin":{"x":1039,"y":1148},"end":{"x":1033.5,"y":1143.5}},{"type":"Q","begin":{"x":1028,"y":1139},"end":{"x":1015,"y":1141}},{"type":"Q","begin":{"x":1010,"y":1142},"end":{"x":985.5,"y":1149}},{"type":"Q","begin":{"x":961,"y":1156},"end":{"x":923,"y":1162}},{"type":"L","x":889,"y":1168},{"type":"L","x":881,"y":1129}],"track":[{"x":893,"y":1143,"size":85},{"x":1074,"y":1060,"size":80},{"x":1158,"y":1112,"size":80},{"x":1050,"y":1290}]},{"outline":[{"type":"M","x":1085,"y":1254},{"type":"Q","begin":{"x":1096,"y":1264},"end":{"x":1102,"y":1274.5}},{"type":"Q","begin":{"x":1108,"y":1285},"end":{"x":1104,"y":1290}},{"type":"Q","begin":{"x":1101,"y":1294},"end":{"x":1093,"y":1294.5}},{"type":"Q","begin":{"x":1085,"y":1295},"end":{"x":1054.5,"y":1296.5}},{"type":"Q","begin":{"x":1024,"y":1298},"end":{"x":989,"y":1301}},{"type":"L","x":934,"y":1307},{"type":"L","x":906,"y":1310},{"type":"L","x":901,"y":1262},{"type":"Q","begin":{"x":954,"y":1253},"end":{"x":965,"y":1251}},{"type":"L","x":1026,"y":1241},{"type":"L","x":1085,"y":1254}],"track":[{"x":903,"y":1283},{"x":1086,"y":1273}]},{"outline":[{"type":"M","x":1187,"y":1443},{"type":"Q","begin":{"x":1159,"y":1446},"end":{"x":1109.5,"y":1449}},{"type":"Q","begin":{"x":1060,"y":1452},"end":{"x":1045,"y":1453.5}},{"type":"Q","begin":{"x":1030,"y":1455},"end":{"x":963,"y":1462}},{"type":"Q","begin":{"x":896,"y":1469},"end":{"x":859,"y":1472}},{"type":"Q","begin":{"x":822,"y":1475},"end":{"x":806,"y":1474}},{"type":"L","x":764,"y":1474},{"type":"L","x":761,"y":1416},{"type":"Q","begin":{"x":831,"y":1409},"end":{"x":867,"y":1405}},{"type":"Q","begin":{"x":903,"y":1401},"end":{"x":983,"y":1391.5}},{"type":"Q","begin":{"x":1063,"y":1382},"end":{"x":1093.5,"y":1377.5}},{"type":"Q","begin":{"x":1124,"y":1373},"end":{"x":1137,"y":1373}},{"type":"Q","begin":{"x":1155,"y":1374},"end":{"x":1173,"y":1380.5}},{"type":"Q","begin":{"x":1191,"y":1387},"end":{"x":1196,"y":1386}},{"type":"L","x":1187,"y":1443}],"track":[{"x":773,"y":1440},{"x":1183,"y":1410}]},{"outline":[{"type":"M","x":1452,"y":1649},{"type":"Q","begin":{"x":1364,"y":1653},"end":{"x":1337.5,"y":1654}},{"type":"Q","begin":{"x":1311,"y":1655},"end":{"x":1120,"y":1665}},{"type":"L","x":925,"y":1675},{"type":"Q","begin":{"x":832,"y":1680},"end":{"x":778,"y":1684}},{"type":"L","x":639,"y":1696},{"type":"Q","begin":{"x":579,"y":1701},"end":{"x":539,"y":1701.5}},{"type":"Q","begin":{"x":499,"y":1702},"end":{"x":478,"y":1698}},{"type":"L","x":441,"y":1693},{"type":"L","x":447,"y":1626},{"type":"Q","begin":{"x":528,"y":1620},"end":{"x":569,"y":1617}},{"type":"L","x":753,"y":1607},{"type":"Q","begin":{"x":771,"y":1606},"end":{"x":959,"y":1590}},{"type":"L","x":1137,"y":1576},{"type":"Q","begin":{"x":1228,"y":1570},"end":{"x":1290.5,"y":1562.5}},{"type":"Q","begin":{"x":1353,"y":1555},"end":{"x":1376,"y":1554}},{"type":"Q","begin":{"x":1403,"y":1553},"end":{"x":1420.5,"y":1557.5}},{"type":"Q","begin":{"x":1438,"y":1562},"end":{"x":1464.5,"y":1575}},{"type":"Q","begin":{"x":1491,"y":1588},"end":{"x":1508.5,"y":1599.5}},{"type":"Q","begin":{"x":1526,"y":1611},"end":{"x":1532,"y":1609}},{"type":"L","x":1452,"y":1649}],"track":[{"x":442,"y":1656},{"x":1426,"y":1603}]}]