[{"outline":[{"type":"M","x":151,"y":852},{"type":"L","x":191,"y":825},{"type":"Q","begin":{"x":232,"y":797},"end":{"x":271,"y":767}},{"type":"Q","begin":{"x":310,"y":737},"end":{"x":355.5,"y":697}},{"type":"Q","begin":{"x":401,"y":657},"end":{"x":448.5,"y":609}},{"type":"Q","begin":{"x":496,"y":561},"end":{"x":527,"y":522.5}},{"type":"Q","begin":{"x":558,"y":484},"end":{"x":579,"y":451.5}},{"type":"Q","begin":{"x":600,"y":419},"end":{"x":611,"y":392.5}},{"type":"Q","begin":{"x":622,"y":366},"end":{"x":624,"y":337}},{"type":"Q","begin":{"x":626,"y":308},"end":{"x":633.5,"y":301}},{"type":"Q","begin":{"x":641,"y":294},"end":{"x":660,"y":294}},{"type":"Q","begin":{"x":682,"y":295},"end":{"x":716.5,"y":317.5}},{"type":"Q","begin":{"x":751,"y":340},"end":{"x":777,"y":368.5}},{"type":"Q","begin":{"x":803,"y":397},"end":{"x":796,"y":417}},{"type":"Q","begin":{"x":792,"y":427},"end":{"x":765,"y":447}},{"type":"Q","begin":{"x":738,"y":467},"end":{"x":732.5,"y":472}},{"type":"Q","begin":{"x":727,"y":477},"end":{"x":700,"y":507}},{"type":"Q","begin":{"x":673,"y":537},"end":{"x":619,"y":587.5}},{"type":"Q","begin":{"x":565,"y":638},"end":{"x":520.5,"y":674.5}},{"type":"Q","begin":{"x":476,"y":711},"end":{"x":410,"y":753.5}},{"type":"Q","begin":{"x":344,"y":796},"end":{"x":297.5,"y":818}},{"type":"Q","begin":{"x":251,"y":840},"end":{"x":200,"y":859}},{"type":"L","x":166,"y":872},{"type":"Q","begin":{"x":148,"y":879},"end":{"x":143.5,"y":870}},{"type":"Q","begin":{"x":139,"y":861},"end":{"x":151,"y":852}}],"track":[{"x":740,"y":340},{"x":470,"y":650},{"x":156,"y":860}]},{"outline":[{"type":"M","x":1804,"y":720},{"type":"L","x":1875,"y":738},{"type":"Q","begin":{"x":1904,"y":746},"end":{"x":1903.5,"y":761.5}},{"type":"Q","begin":{"x":1903,"y":777},"end":{"x":1878,"y":783}},{"type":"L","x":1800,"y":802},{"type":"Q","begin":{"x":1771,"y":809},"end":{"x":1714,"y":820.5}},{"type":"Q","begin":{"x":1657,"y":832},"end":{"x":1615,"y":837}},{"type":"Q","begin":{"x":1573,"y":842},"end":{"x":1537,"y":835}},{"type":"Q","begin":{"x":1506,"y":830},"end":{"x":1476,"y":813}},{"type":"Q","begin":{"x":1446,"y":796},"end":{"x":1396.5,"y":747}},{"type":"Q","begin":{"x":1347,"y":698},"end":{"x":1270,"y":606.5}},{"type":"Q","begin":{"x":1193,"y":515},"end":{"x":1165,"y":479}},{"type":"L","x":1068,"y":358},{"type":"Q","begin":{"x":1029,"y":312},"end":{"x":996.5,"y":277.5}},{"type":"Q","begin":{"x":964,"y":243},"end":{"x":947,"y":234}},{"type":"L","x":905,"y":217},{"type":"Q","begin":{"x":885,"y":208},"end":{"x":883.5,"y":195.5}},{"type":"Q","begin":{"x":882,"y":183},"end":{"x":890.5,"y":177}},{"type":"Q","begin":{"x":899,"y":171},"end":{"x":915,"y":172}},{"type":"Q","begin":{"x":953,"y":175},"end":{"x":976.5,"y":184}},{"type":"Q","begin":{"x":1000,"y":193},"end":{"x":1032,"y":223}},{"type":"Q","begin":{"x":1064,"y":253},"end":{"x":1130,"y":323}},{"type":"Q","begin":{"x":1196,"y":393},"end":{"x":1254.5,"y":445}},{"type":"Q","begin":{"x":1313,"y":497},"end":{"x":1381.5,"y":543}},{"type":"Q","begin":{"x":1450,"y":589},"end":{"x":1534.5,"y":628.5}},{"type":"Q","begin":{"x":1619,"y":668},"end":{"x":1678.5,"y":686}},{"type":"Q","begin":{"x":1738,"y":704},"end":{"x":1804,"y":720}}],"track":[{"x":913,"y":193},{"x":1553,"y":763},{"x":1863,"y":760}]},{"outline":[{"type":"M","x":735,"y":746},{"type":"Q","begin":{"x":710,"y":754},"end":{"x":691.5,"y":759.5}},{"type":"Q","begin":{"x":673,"y":765},"end":{"x":646,"y":772.5}},{"type":"Q","begin":{"x":619,"y":780},"end":{"x":605,"y":778}},{"type":"Q","begin":{"x":592,"y":777},"end":{"x":566,"y":764.5}},{"type":"Q","begin":{"x":540,"y":752},"end":{"x":527,"y":738}},{"type":"Q","begin":{"x":514,"y":724},"end":{"x":517,"y":716}},{"type":"Q","begin":{"x":519,"y":709},"end":{"x":535,"y":704}},{"type":"L","x":581,"y":702},{"type":"L","x":673,"y":694},{"type":"Q","begin":{"x":698,"y":692},"end":{"x":762.5,"y":682.5}},{"type":"Q","begin":{"x":827,"y":673},"end":{"x":907,"y":663}},{"type":"Q","begin":{"x":987,"y":653},"end":{"x":1024,"y":646}},{"type":"Q","begin":{"x":1061,"y":639},"end":{"x":1102,"y":626.5}},{"type":"Q","begin":{"x":1143,"y":614},"end":{"x":1160,"y":614}},{"type":"Q","begin":{"x":1177,"y":615},"end":{"x":1200,"y":624.5}},{"type":"Q","begin":{"x":1223,"y":634},"end":{"x":1251,"y":650.5}},{"type":"Q","begin":{"x":1279,"y":667},"end":{"x":1296.5,"y":679.5}},{"type":"Q","begin":{"x":1314,"y":692},"end":{"x":1314.5,"y":700}},{"type":"Q","begin":{"x":1315,"y":708},"end":{"x":1313,"y":714}},{"type":"Q","begin":{"x":1312,"y":716},"end":{"x":1291.5,"y":747}},{"type":"Q","begin":{"x":1271,"y":778},"end":{"x":1259,"y":830}},{"type":"L","x":1212,"y":1022},{"type":"Q","begin":{"x":1200,"y":1068},"end":{"x":1182,"y":1105}},{"type":"Q","begin":{"x":1164,"y":1142},"end":{"x":1139,"y":1169.5}},{"type":"Q","begin":{"x":1114,"y":1197},"end":{"x":1078.5,"y":1220.5}},{"type":"Q","begin":{"x":1043,"y":1244},"end":{"x":1024,"y":1235}},{"type":"Q","begin":{"x":1013,"y":1231},"end":{"x":1005.5,"y":1219.5}},{"type":"Q","begin":{"x":998,"y":1208},"end":{"x":984,"y":1178}},{"type":"Q","begin":{"x":970,"y":1148},"end":{"x":955,"y":1128}},{"type":"L","x":925,"y":1095},{"type":"L","x":898,"y":1065},{"type":"Q","begin":{"x":889,"y":1056},"end":{"x":894.5,"y":1048}},{"type":"Q","begin":{"x":900,"y":1040},"end":{"x":914,"y":1043}},{"type":"L","x":973,"y":1058},{"type":"Q","begin":{"x":983,"y":1061},"end":{"x":1010.5,"y":1064.5}},{"type":"Q","begin":{"x":1038,"y":1068},"end":{"x":1047,"y":1065}},{"type":"Q","begin":{"x":1061,"y":1061},"end":{"x":1078,"y":1033}},{"type":"Q","begin":{"x":1095,"y":1005},"end":{"x":1111,"y":958}},{"type":"L","x":1145,"y":842},{"type":"Q","begin":{"x":1162,"y":783},"end":{"x":1160,"y":755}},{"type":"Q","begin":{"x":1158,"y":739},"end":{"x":1151.5,"y":728}},{"type":"Q","begin":{"x":1145,"y":717},"end":{"x":1133.5,"y":710}},{"type":"Q","begin":{"x":1122,"y":703},"end":{"x":1095,"y":702}},{"type":"Q","begin":{"x":1061,"y":702},"end":{"x":993,"y":708}},{"type":"Q","begin":{"x":925,"y":714},"end":{"x":913,"y":716}},{"type":"L","x":791,"y":736},{"type":"L","x":735,"y":746}],"track":[{"x":550,"y":753},{"x":963,"y":680},{"x":1140,"y":650},{"x":1210,"y":650},{"x":1273,"y":720},{"x":1216,"y":783},{"x":1040,"y":1216},{"x":915,"y":1061}]},{"outline":[{"type":"M","x":791,"y":736},{"type":"Q","begin":{"x":815,"y":758},"end":{"x":836,"y":776}},{"type":"Q","begin":{"x":857,"y":794},"end":{"x":872,"y":815.5}},{"type":"Q","begin":{"x":887,"y":837},"end":{"x":884,"y":850}},{"type":"Q","begin":{"x":881,"y":859},"end":{"x":860,"y":877.5}},{"type":"Q","begin":{"x":839,"y":896},"end":{"x":824,"y":911}},{"type":"L","x":755,"y":987},{"type":"Q","begin":{"x":710,"y":1036},"end":{"x":654,"y":1080.5}},{"type":"Q","begin":{"x":598,"y":1125},"end":{"x":541,"y":1160}},{"type":"Q","begin":{"x":484,"y":1195},"end":{"x":450,"y":1210}},{"type":"L","x":391,"y":1236},{"type":"Q","begin":{"x":351,"y":1254},"end":{"x":350.5,"y":1239}},{"type":"Q","begin":{"x":350,"y":1224},"end":{"x":372,"y":1208}},{"type":"L","x":417,"y":1176},{"type":"Q","begin":{"x":439,"y":1160},"end":{"x":503.5,"y":1101.5}},{"type":"Q","begin":{"x":568,"y":1043},"end":{"x":598,"y":1010.5}},{"type":"Q","begin":{"x":628,"y":978},"end":{"x":659,"y":932}},{"type":"Q","begin":{"x":690,"y":886},"end":{"x":704.5,"y":854.5}},{"type":"Q","begin":{"x":719,"y":823},"end":{"x":725,"y":793}},{"type":"L","x":735,"y":746},{"type":"L","x":791,"y":736}],"track":[{"x":830,"y":790},{"x":660,"y":1010},{"x":383,"y":1230}]},{"outline":[{"type":"M","x":895,"y":1673},{"type":"L","x":891,"y":1419},{"type":"Q","begin":{"x":890,"y":1409},"end":{"x":886,"y":1365}},{"type":"Q","begin":{"x":882,"y":1321},"end":{"x":876,"y":1305}},{"type":"L","x":858,"y":1269},{"type":"Q","begin":{"x":849,"y":1246},"end":{"x":856.5,"y":1237.5}},{"type":"Q","begin":{"x":864,"y":1229},"end":{"x":891,"y":1232}},{"type":"Q","begin":{"x":910,"y":1235},"end":{"x":954,"y":1248.5}},{"type":"Q","begin":{"x":998,"y":1262},"end":{"x":1018.5,"y":1274.5}},{"type":"Q","begin":{"x":1039,"y":1287},"end":{"x":1042,"y":1297.5}},{"type":"Q","begin":{"x":1045,"y":1308},"end":{"x":1036,"y":1332}},{"type":"Q","begin":{"x":1028,"y":1352},"end":{"x":1024.5,"y":1371}},{"type":"Q","begin":{"x":1021,"y":1390},"end":{"x":1019,"y":1433}},{"type":"L","x":1007,"y":1661},{"type":"Q","begin":{"x":947,"y":1767},"end":{"x":895,"y":1673}}],"track":[{"x":956,"y":1246},{"x":953,"y":1696}]},{"outline":[{"type":"M","x":1007,"y":1661},{"type":"Q","begin":{"x":1087,"y":1660},"end":{"x":1127,"y":1658}},{"type":"L","x":1261,"y":1650},{"type":"L","x":1372,"y":1647},{"type":"Q","begin":{"x":1442,"y":1670.5},"end":{"x":1372,"y":1700}},{"type":"Q","begin":{"x":1227,"y":1716},"end":{"x":1111.5,"y":1729}},{"type":"Q","begin":{"x":996,"y":1742},"end":{"x":892.5,"y":1757}},{"type":"Q","begin":{"x":789,"y":1772},"end":{"x":711,"y":1790.5}},{"type":"Q","begin":{"x":633,"y":1809},"end":{"x":580,"y":1826.5}},{"type":"Q","begin":{"x":527,"y":1844},"end":{"x":497.5,"y":1861.5}},{"type":"Q","begin":{"x":468,"y":1879},"end":{"x":458,"y":1877}},{"type":"Q","begin":{"x":443,"y":1876},"end":{"x":420.5,"y":1851}},{"type":"Q","begin":{"x":398,"y":1826},"end":{"x":384.5,"y":1802}},{"type":"Q","begin":{"x":371,"y":1778},"end":{"x":372,"y":1761}},{"type":"Q","begin":{"x":372,"y":1747},"end":{"x":386,"y":1724}},{"type":"L","x":418,"y":1672},{"type":"Q","begin":{"x":444,"y":1625},"end":{"x":453.5,"y":1567.5}},{"type":"Q","begin":{"x":463,"y":1510},"end":{"x":458,"y":1471}},{"type":"Q","begin":{"x":454,"y":1450},"end":{"x":444,"y":1420.5}},{"type":"Q","begin":{"x":434,"y":1391},"end":{"x":438.5,"y":1384}},{"type":"Q","begin":{"x":443,"y":1377},"end":{"x":453.5,"y":1373}},{"type":"Q","begin":{"x":464,"y":1369},"end":{"x":487,"y":1376}},{"type":"Q","begin":{"x":512,"y":1385},"end":{"x":541.5,"y":1403}},{"type":"Q","begin":{"x":571,"y":1421},"end":{"x":590.5,"y":1440.5}},{"type":"Q","begin":{"x":610,"y":1460},"end":{"x":610,"y":1473}},{"type":"Q","begin":{"x":609,"y":1481},"end":{"x":602,"y":1495}},{"type":"L","x":583,"y":1529},{"type":"Q","begin":{"x":573,"y":1548},"end":{"x":569,"y":1562}},{"type":"L","x":537,"y":1667},{"type":"Q","begin":{"x":529,"y":1694},"end":{"x":531.5,"y":1699}},{"type":"Q","begin":{"x":534,"y":1704},"end":{"x":584,"y":1699}},{"type":"L","x":895,"y":1673},{"type":"L","x":1007,"y":1661}],"track":[{"x":526,"y":1396},{"x":396,"y":1688},{"x":355,"y":1775},{"x":436,"y":1878},{"x":715,"y":1737},{"x":1363,"y":1686}]},{"outline":[{"type":"M","x":1372,"y":1647},{"type":"L","x":1375,"y":1544},{"type":"Q","begin":{"x":1375,"y":1533},"end":{"x":1372,"y":1482.5}},{"type":"Q","begin":{"x":1369,"y":1432},"end":{"x":1365,"y":1416}},{"type":"L","x":1351,"y":1373},{"type":"Q","begin":{"x":1348,"y":1355},"end":{"x":1355,"y":1347.5}},{"type":"Q","begin":{"x":1362,"y":1340},"end":{"x":1388,"y":1343}},{"type":"Q","begin":{"x":1415,"y":1348},"end":{"x":1443,"y":1358.5}},{"type":"Q","begin":{"x":1471,"y":1369},"end":{"x":1504,"y":1387}},{"type":"Q","begin":{"x":1537,"y":1405},"end":{"x":1539,"y":1416}},{"type":"Q","begin":{"x":1541,"y":1427},"end":{"x":1528,"y":1459.5}},{"type":"Q","begin":{"x":1515,"y":1492},"end":{"x":1511,"y":1520}},{"type":"L","x":1484,"y":1704},{"type":"Q","begin":{"x":1477,"y":1746},"end":{"x":1465.5,"y":1784}},{"type":"Q","begin":{"x":1454,"y":1822},"end":{"x":1440,"y":1840}},{"type":"Q","begin":{"x":1426,"y":1858},"end":{"x":1411,"y":1858.5}},{"type":"Q","begin":{"x":1396,"y":1859},"end":{"x":1382.5,"y":1838}},{"type":"Q","begin":{"x":1369,"y":1817},"end":{"x":1367.5,"y":1799.5}},{"type":"Q","begin":{"x":1366,"y":1782},"end":{"x":1368,"y":1766}},{"type":"L","x":1372,"y":1700},{"type":"L","x":1372,"y":1647}],"track":[{"x":1456,"y":1370},{"x":1406,"y":1840}]}]