[{"outline":[{"type":"M","x":392,"y":959},{"type":"Q","begin":{"x":396,"y":1000},"end":{"x":392,"y":1053}},{"type":"Q","begin":{"x":388,"y":1106},"end":{"x":376,"y":1145}},{"type":"Q","begin":{"x":364,"y":1184},"end":{"x":345.5,"y":1220}},{"type":"Q","begin":{"x":327,"y":1256},"end":{"x":303.5,"y":1274.5}},{"type":"Q","begin":{"x":280,"y":1293},"end":{"x":266,"y":1292}},{"type":"Q","begin":{"x":244,"y":1292},"end":{"x":226,"y":1267.5}},{"type":"Q","begin":{"x":208,"y":1243},"end":{"x":203,"y":1213.5}},{"type":"Q","begin":{"x":198,"y":1184},"end":{"x":197,"y":1154}},{"type":"Q","begin":{"x":196,"y":1124},"end":{"x":203,"y":1107}},{"type":"Q","begin":{"x":205,"y":1102},"end":{"x":220.5,"y":1080.5}},{"type":"Q","begin":{"x":236,"y":1059},"end":{"x":254,"y":1023.5}},{"type":"Q","begin":{"x":272,"y":988},"end":{"x":279.5,"y":970}},{"type":"Q","begin":{"x":287,"y":952},"end":{"x":297,"y":914.5}},{"type":"Q","begin":{"x":307,"y":877},"end":{"x":309,"y":854}},{"type":"Q","begin":{"x":311,"y":831},"end":{"x":317.5,"y":822.5}},{"type":"Q","begin":{"x":324,"y":814},"end":{"x":335,"y":814}},{"type":"Q","begin":{"x":346,"y":815},"end":{"x":361.5,"y":853}},{"type":"Q","begin":{"x":377,"y":891},"end":{"x":383,"y":914.5}},{"type":"Q","begin":{"x":389,"y":938},"end":{"x":392,"y":959}}],"track":[{"x":326,"y":836},{"x":250,"y":1276}]},{"outline":[{"type":"M","x":1427,"y":1026},{"type":"L","x":1528,"y":1143},{"type":"Q","begin":{"x":1561,"y":1182},"end":{"x":1590.5,"y":1203.5}},{"type":"Q","begin":{"x":1620,"y":1225},"end":{"x":1653,"y":1246}},{"type":"L","x":1713,"y":1287},{"type":"Q","begin":{"x":1738,"y":1305},"end":{"x":1748.5,"y":1320.5}},{"type":"Q","begin":{"x":1759,"y":1336},"end":{"x":1757,"y":1361}},{"type":"Q","begin":{"x":1755,"y":1378},"end":{"x":1745,"y":1396}},{"type":"Q","begin":{"x":1735,"y":1414},"end":{"x":1680.5,"y":1447.5}},{"type":"Q","begin":{"x":1626,"y":1481},"end":{"x":1516,"y":1504.5}},{"type":"Q","begin":{"x":1406,"y":1528},"end":{"x":1297,"y":1528}},{"type":"Q","begin":{"x":1194,"y":1529},"end":{"x":1103,"y":1510.5}},{"type":"Q","begin":{"x":1012,"y":1492},"end":{"x":947,"y":1463.5}},{"type":"Q","begin":{"x":882,"y":1435},"end":{"x":832,"y":1397}},{"type":"Q","begin":{"x":782,"y":1359},"end":{"x":741.5,"y":1309}},{"type":"Q","begin":{"x":701,"y":1259},"end":{"x":672.5,"y":1201.5}},{"type":"Q","begin":{"x":644,"y":1144},"end":{"x":631,"y":1105}},{"type":"Q","begin":{"x":618,"y":1066},"end":{"x":607,"y":1019}},{"type":"L","x":581,"y":914},{"type":"Q","begin":{"x":577,"y":902},"end":{"x":563.5,"y":868.5}},{"type":"Q","begin":{"x":550,"y":835},"end":{"x":555,"y":827}},{"type":"Q","begin":{"x":560,"y":819},"end":{"x":569.5,"y":816}},{"type":"Q","begin":{"x":579,"y":813},"end":{"x":595,"y":819}},{"type":"Q","begin":{"x":607,"y":825},"end":{"x":623,"y":838}},{"type":"Q","begin":{"x":639,"y":851},"end":{"x":644.5,"y":860.5}},{"type":"Q","begin":{"x":650,"y":870},"end":{"x":659,"y":906}},{"type":"L","x":680,"y":1000},{"type":"Q","begin":{"x":694,"y":1064},"end":{"x":717,"y":1107.5}},{"type":"Q","begin":{"x":740,"y":1151},"end":{"x":776.5,"y":1195.5}},{"type":"Q","begin":{"x":813,"y":1240},"end":{"x":860,"y":1276}},{"type":"Q","begin":{"x":907,"y":1312},"end":{"x":959,"y":1333}},{"type":"Q","begin":{"x":1011,"y":1354},"end":{"x":1059.5,"y":1361.5}},{"type":"Q","begin":{"x":1108,"y":1369},"end":{"x":1172.5,"y":1370.5}},{"type":"Q","begin":{"x":1237,"y":1372},"end":{"x":1289,"y":1370}},{"type":"Q","begin":{"x":1355,"y":1368},"end":{"x":1395.5,"y":1352.5}},{"type":"Q","begin":{"x":1436,"y":1337},"end":{"x":1444,"y":1319}},{"type":"Q","begin":{"x":1452,"y":1301},"end":{"x":1454,"y":1276.5}},{"type":"Q","begin":{"x":1456,"y":1252},"end":{"x":1441,"y":1204}},{"type":"L","x":1391,"y":1049},{"type":"Q","begin":{"x":1383,"y":1025},"end":{"x":1396,"y":1015.5}},{"type":"Q","begin":{"x":1409,"y":1006},"end":{"x":1427,"y":1026}}],"track":[{"x":595,"y":835},{"x":758,"y":1288},{"x":1163,"y":1462,"size":140},{"x":1665,"y":1394,"size":180},{"x":1414,"y":1043}]},{"outline":[{"type":"M","x":845,"y":590},{"type":"L","x":819,"y":552},{"type":"Q","begin":{"x":808,"y":537},"end":{"x":815,"y":528}},{"type":"Q","begin":{"x":822,"y":519},"end":{"x":833,"y":521}},{"type":"L","x":885,"y":532},{"type":"Q","begin":{"x":898,"y":535},"end":{"x":934.5,"y":547.5}},{"type":"Q","begin":{"x":971,"y":560},"end":{"x":991,"y":567}},{"type":"Q","begin":{"x":1011,"y":574},"end":{"x":1036.5,"y":587}},{"type":"Q","begin":{"x":1062,"y":600},"end":{"x":1076,"y":617}},{"type":"Q","begin":{"x":1090,"y":634},"end":{"x":1098,"y":664}},{"type":"Q","begin":{"x":1106,"y":694},"end":{"x":1096,"y":736}},{"type":"Q","begin":{"x":1087,"y":772},"end":{"x":1071.5,"y":787.5}},{"type":"Q","begin":{"x":1056,"y":803},"end":{"x":1040,"y":806}},{"type":"Q","begin":{"x":1024,"y":809},"end":{"x":994,"y":778}},{"type":"Q","begin":{"x":974,"y":759},"end":{"x":955,"y":735}},{"type":"Q","begin":{"x":936,"y":711},"end":{"x":898,"y":662}},{"type":"Q","begin":{"x":860,"y":613},"end":{"x":845,"y":590}}],"track":[{"x":826,"y":526},{"x":1070,"y":726}]},{"outline":[{"type":"M","x":1653,"y":844},{"type":"L","x":1538,"y":693},{"type":"L","x":1445,"y":591},{"type":"Q","begin":{"x":1433,"y":572},"end":{"x":1438,"y":565.5}},{"type":"Q","begin":{"x":1443,"y":559},"end":{"x":1457.5,"y":557.5}},{"type":"Q","begin":{"x":1472,"y":556},"end":{"x":1512,"y":573}},{"type":"L","x":1652,"y":634},{"type":"Q","begin":{"x":1725,"y":666},"end":{"x":1773,"y":705.5}},{"type":"Q","begin":{"x":1821,"y":745},"end":{"x":1836,"y":779}},{"type":"Q","begin":{"x":1851,"y":813},"end":{"x":1850,"y":852}},{"type":"Q","begin":{"x":1848,"y":886},"end":{"x":1836,"y":909.5}},{"type":"Q","begin":{"x":1824,"y":933},"end":{"x":1809,"y":940.5}},{"type":"Q","begin":{"x":1794,"y":948},"end":{"x":1780,"y":948.5}},{"type":"Q","begin":{"x":1766,"y":949},"end":{"x":1733.5,"y":928.5}},{"type":"Q","begin":{"x":1701,"y":908},"end":{"x":1653,"y":844}}],"track":[{"x":1460,"y":576},{"x":1824,"y":891}]}]