[{"outline":[{"type":"M","x":507,"y":853},{"type":"L","x":377,"y":871},{"type":"Q","begin":{"x":311,"y":881},"end":{"x":285,"y":882}},{"type":"Q","begin":{"x":259,"y":883},"end":{"x":233.5,"y":879}},{"type":"Q","begin":{"x":208,"y":875},"end":{"x":185.5,"y":866.5}},{"type":"Q","begin":{"x":163,"y":858},"end":{"x":158,"y":844}},{"type":"Q","begin":{"x":153,"y":830},"end":{"x":158,"y":823}},{"type":"Q","begin":{"x":161,"y":818},"end":{"x":178.5,"y":817.5}},{"type":"Q","begin":{"x":196,"y":817},"end":{"x":215.5,"y":814.5}},{"type":"Q","begin":{"x":235,"y":812},"end":{"x":280.5,"y":806}},{"type":"Q","begin":{"x":326,"y":800},"end":{"x":362,"y":793}},{"type":"L","x":537,"y":760},{"type":"L","x":630,"y":742},{"type":"L","x":666,"y":731},{"type":"Q","begin":{"x":676,"y":728},"end":{"x":697,"y":719}},{"type":"Q","begin":{"x":718,"y":710},"end":{"x":730,"y":708}},{"type":"Q","begin":{"x":745,"y":706},"end":{"x":783,"y":715.5}},{"type":"Q","begin":{"x":821,"y":725},"end":{"x":836,"y":740}},{"type":"Q","begin":{"x":851,"y":755},"end":{"x":849,"y":766}},{"type":"Q","begin":{"x":847,"y":776},"end":{"x":832.5,"y":785.5}},{"type":"Q","begin":{"x":818,"y":795},"end":{"x":782,"y":802}},{"type":"L","x":718,"y":816},{"type":"L","x":624,"y":834},{"type":"L","x":507,"y":853}],"track":[{"x":173,"y":848},{"x":806,"y":743}]},{"outline":[{"type":"M","x":537,"y":760},{"type":"L","x":531,"y":505},{"type":"Q","begin":{"x":529,"y":450},"end":{"x":525.5,"y":404.5}},{"type":"Q","begin":{"x":522,"y":359},"end":{"x":517,"y":334}},{"type":"Q","begin":{"x":512,"y":309},"end":{"x":507,"y":292}},{"type":"L","x":493,"y":255},{"type":"Q","begin":{"x":484,"y":230},"end":{"x":491,"y":222}},{"type":"Q","begin":{"x":498,"y":214},"end":{"x":518,"y":213}},{"type":"Q","begin":{"x":540,"y":213},"end":{"x":562,"y":222}},{"type":"Q","begin":{"x":584,"y":231},"end":{"x":613,"y":246}},{"type":"Q","begin":{"x":642,"y":261},"end":{"x":660.5,"y":281.5}},{"type":"Q","begin":{"x":679,"y":302},"end":{"x":679.5,"y":316.5}},{"type":"Q","begin":{"x":680,"y":331},"end":{"x":669,"y":362}},{"type":"Q","begin":{"x":663,"y":379},"end":{"x":657.5,"y":406.5}},{"type":"Q","begin":{"x":652,"y":434},"end":{"x":647.5,"y":467}},{"type":"Q","begin":{"x":643,"y":500},"end":{"x":640,"y":563}},{"type":"L","x":630,"y":742},{"type":"L","x":624,"y":834},{"type":"L","x":616,"y":1012},{"type":"L","x":614,"y":1052},{"type":"L","x":610,"y":1307},{"type":"L","x":608,"y":1457},{"type":"Q","begin":{"x":607,"y":1469},"end":{"x":603.5,"y":1567}},{"type":"Q","begin":{"x":600,"y":1665},"end":{"x":596.5,"y":1703}},{"type":"Q","begin":{"x":593,"y":1741},"end":{"x":584,"y":1771.5}},{"type":"Q","begin":{"x":575,"y":1802},"end":{"x":559.5,"y":1819.5}},{"type":"Q","begin":{"x":544,"y":1837},"end":{"x":531,"y":1836}},{"type":"Q","begin":{"x":518,"y":1836},"end":{"x":503,"y":1814.5}},{"type":"Q","begin":{"x":488,"y":1793},"end":{"x":474,"y":1753.5}},{"type":"Q","begin":{"x":460,"y":1714},"end":{"x":457,"y":1693.5}},{"type":"Q","begin":{"x":454,"y":1673},"end":{"x":458,"y":1644}},{"type":"Q","begin":{"x":460,"y":1623},"end":{"x":472.5,"y":1570.5}},{"type":"Q","begin":{"x":485,"y":1518},"end":{"x":491,"y":1479}},{"type":"Q","begin":{"x":497,"y":1440},"end":{"x":500.5,"y":1397}},{"type":"Q","begin":{"x":504,"y":1354},"end":{"x":510,"y":1268}},{"type":"L","x":522,"y":1095},{"type":"L","x":537,"y":760}],"track":[{"x":585,"y":243,"size":140},{"x":565,"y":925},{"x":542,"y":1815}]},{"outline":[{"type":"M","x":522,"y":1095},{"type":"Q","begin":{"x":497,"y":1140},"end":{"x":476.5,"y":1176.5}},{"type":"Q","begin":{"x":456,"y":1213},"end":{"x":419,"y":1268}},{"type":"Q","begin":{"x":382,"y":1323},"end":{"x":336,"y":1374}},{"type":"Q","begin":{"x":290,"y":1425},"end":{"x":235.5,"y":1471}},{"type":"Q","begin":{"x":181,"y":1517},"end":{"x":149,"y":1535}},{"type":"L","x":107,"y":1559},{"type":"Q","begin":{"x":88,"y":1570},"end":{"x":81,"y":1565.5}},{"type":"Q","begin":{"x":74,"y":1561},"end":{"x":74,"y":1554.5}},{"type":"Q","begin":{"x":74,"y":1548},"end":{"x":87,"y":1535}},{"type":"L","x":121,"y":1502},{"type":"Q","begin":{"x":142,"y":1482},"end":{"x":186,"y":1428.5}},{"type":"Q","begin":{"x":230,"y":1375},"end":{"x":273,"y":1314.5}},{"type":"Q","begin":{"x":316,"y":1254},"end":{"x":356,"y":1188.5}},{"type":"Q","begin":{"x":396,"y":1123},"end":{"x":422.5,"y":1065.5}},{"type":"Q","begin":{"x":449,"y":1008},"end":{"x":480,"y":925}},{"type":"L","x":507,"y":853},{"type":"Q","begin":{"x":631.5,"y":817},"end":{"x":522,"y":1095}}],"track":[{"x":545,"y":871},{"x":330,"y":1305},{"x":92,"y":1555}]},{"outline":[{"type":"M","x":616,"y":1012},{"type":"Q","begin":{"x":641,"y":1022},"end":{"x":666,"y":1032.5}},{"type":"Q","begin":{"x":691,"y":1043},"end":{"x":718.5,"y":1060}},{"type":"Q","begin":{"x":746,"y":1077},"end":{"x":768,"y":1101.5}},{"type":"Q","begin":{"x":790,"y":1126},"end":{"x":799,"y":1151.5}},{"type":"Q","begin":{"x":808,"y":1177},"end":{"x":808,"y":1206}},{"type":"Q","begin":{"x":807,"y":1235},"end":{"x":793.5,"y":1251.5}},{"type":"Q","begin":{"x":780,"y":1268},"end":{"x":761,"y":1268.5}},{"type":"Q","begin":{"x":742,"y":1269},"end":{"x":714,"y":1223}},{"type":"Q","begin":{"x":685,"y":1178},"end":{"x":678,"y":1164}},{"type":"L","x":614,"y":1052},{"type":"L","x":616,"y":1012}],"track":[{"x":626,"y":1047},{"x":783,"y":1240}]},{"outline":[{"type":"M","x":1109,"y":875},{"type":"Q","begin":{"x":1191,"y":863},"end":{"x":1233,"y":856}},{"type":"L","x":1401,"y":831},{"type":"L","x":1512,"y":813},{"type":"L","x":1623,"y":796},{"type":"L","x":1689,"y":784},{"type":"L","x":1745,"y":772},{"type":"Q","begin":{"x":1764,"y":770},"end":{"x":1787,"y":770}},{"type":"Q","begin":{"x":1817,"y":772},"end":{"x":1847,"y":780}},{"type":"Q","begin":{"x":1877,"y":788},"end":{"x":1902.5,"y":800}},{"type":"Q","begin":{"x":1928,"y":812},"end":{"x":1950.5,"y":829}},{"type":"Q","begin":{"x":1973,"y":846},"end":{"x":1972.5,"y":860.5}},{"type":"Q","begin":{"x":1972,"y":875},"end":{"x":1959,"y":882.5}},{"type":"Q","begin":{"x":1946,"y":890},"end":{"x":1862,"y":892}},{"type":"L","x":1621,"y":898},{"type":"L","x":1509,"y":906},{"type":"Q","begin":{"x":1449,"y":912},"end":{"x":1358.5,"y":920}},{"type":"Q","begin":{"x":1268,"y":928},"end":{"x":1214,"y":936}},{"type":"L","x":1109,"y":951},{"type":"L","x":999,"y":968},{"type":"Q","begin":{"x":953,"y":975},"end":{"x":920,"y":983.5}},{"type":"Q","begin":{"x":887,"y":992},"end":{"x":878,"y":992}},{"type":"Q","begin":{"x":854,"y":994},"end":{"x":840.5,"y":989}},{"type":"Q","begin":{"x":827,"y":984},"end":{"x":789.5,"y":965}},{"type":"Q","begin":{"x":752,"y":946},"end":{"x":751.5,"y":934}},{"type":"Q","begin":{"x":751,"y":922},"end":{"x":763,"y":914}},{"type":"L","x":797,"y":912},{"type":"L","x":1000,"y":889},{"type":"L","x":1109,"y":875}],"track":[{"x":793,"y":956},{"x":1297,"y":886,"size":145},{"x":1877,"y":815}]},{"outline":[{"type":"M","x":1081,"y":1599},{"type":"L","x":1064,"y":1639},{"type":"Q","begin":{"x":1053,"y":1666},"end":{"x":1034.5,"y":1665}},{"type":"Q","begin":{"x":1016,"y":1664},"end":{"x":1002,"y":1646}},{"type":"Q","begin":{"x":988,"y":1628},"end":{"x":977.5,"y":1606.5}},{"type":"Q","begin":{"x":967,"y":1585},"end":{"x":960,"y":1562.5}},{"type":"Q","begin":{"x":953,"y":1540},"end":{"x":952.5,"y":1522.5}},{"type":"Q","begin":{"x":952,"y":1505},"end":{"x":964,"y":1448}},{"type":"Q","begin":{"x":968,"y":1428},"end":{"x":978.5,"y":1337}},{"type":"Q","begin":{"x":989,"y":1246},"end":{"x":990,"y":1224}},{"type":"L","x":999,"y":968},{"type":"L","x":1000,"y":889},{"type":"L","x":1005,"y":706},{"type":"Q","begin":{"x":1006,"y":657},"end":{"x":1002,"y":620}},{"type":"Q","begin":{"x":998,"y":583},"end":{"x":991,"y":554}},{"type":"Q","begin":{"x":984,"y":525},"end":{"x":973,"y":501}},{"type":"Q","begin":{"x":962,"y":477},"end":{"x":965.5,"y":468.5}},{"type":"Q","begin":{"x":969,"y":460},"end":{"x":982.5,"y":455.5}},{"type":"Q","begin":{"x":996,"y":451},"end":{"x":1020,"y":455}},{"type":"Q","begin":{"x":1054,"y":462},"end":{"x":1079.5,"y":473}},{"type":"Q","begin":{"x":1105,"y":484},"end":{"x":1119.5,"y":497.5}},{"type":"Q","begin":{"x":1134,"y":511},"end":{"x":1136,"y":521.5}},{"type":"Q","begin":{"x":1138,"y":532},"end":{"x":1131,"y":556}},{"type":"Q","begin":{"x":1125,"y":574},"end":{"x":1119.5,"y":637.5}},{"type":"Q","begin":{"x":1114,"y":701},"end":{"x":1114,"y":713}},{"type":"L","x":1109,"y":875},{"type":"L","x":1109,"y":951},{"type":"L","x":1103,"y":1215},{"type":"L","x":1100,"y":1268},{"type":"L","x":1090,"y":1528},{"type":"L","x":1081,"y":1599}],"track":[{"x":1053,"y":478,"size":160},{"x":1051,"y":1054,"size":135},{"x":1025,"y":1640}]},{"outline":[{"type":"M","x":1512,"y":813},{"type":"L","x":1503,"y":533},{"type":"Q","begin":{"x":1502,"y":510},"end":{"x":1495.5,"y":462.5}},{"type":"Q","begin":{"x":1489,"y":415},"end":{"x":1484,"y":391.5}},{"type":"Q","begin":{"x":1479,"y":368},"end":{"x":1469.5,"y":342}},{"type":"Q","begin":{"x":1460,"y":316},"end":{"x":1455.5,"y":301}},{"type":"Q","begin":{"x":1451,"y":286},"end":{"x":1457.5,"y":278}},{"type":"Q","begin":{"x":1464,"y":270},"end":{"x":1485,"y":269}},{"type":"Q","begin":{"x":1502,"y":269},"end":{"x":1525,"y":273}},{"type":"Q","begin":{"x":1548,"y":277},"end":{"x":1567,"y":283}},{"type":"Q","begin":{"x":1586,"y":289},"end":{"x":1610,"y":300.5}},{"type":"Q","begin":{"x":1634,"y":312},"end":{"x":1646.5,"y":325}},{"type":"Q","begin":{"x":1659,"y":338},"end":{"x":1660,"y":348}},{"type":"Q","begin":{"x":1661,"y":358},"end":{"x":1652,"y":384}},{"type":"Q","begin":{"x":1648,"y":394},"end":{"x":1642,"y":428}},{"type":"Q","begin":{"x":1636,"y":462},"end":{"x":1634.5,"y":473}},{"type":"Q","begin":{"x":1633,"y":484},"end":{"x":1629.5,"y":549.5}},{"type":"Q","begin":{"x":1626,"y":615},"end":{"x":1626,"y":625}},{"type":"L","x":1623,"y":796},{"type":"L","x":1621,"y":898},{"type":"L","x":1617,"y":1284},{"type":"L","x":1623,"y":1512},{"type":"Q","begin":{"x":1619,"y":1559},"end":{"x":1609,"y":1603.5}},{"type":"Q","begin":{"x":1599,"y":1648},"end":{"x":1571.5,"y":1695.5}},{"type":"Q","begin":{"x":1544,"y":1743},"end":{"x":1514,"y":1731}},{"type":"Q","begin":{"x":1502,"y":1727},"end":{"x":1495,"y":1716.5}},{"type":"Q","begin":{"x":1488,"y":1706},"end":{"x":1473,"y":1673}},{"type":"L","x":1422,"y":1565},{"type":"Q","begin":{"x":1346,"y":1452},"end":{"x":1450,"y":1479}},{"type":"L","x":1486,"y":1493},{"type":"Q","begin":{"x":1490,"y":1462},"end":{"x":1491.5,"y":1447}},{"type":"Q","begin":{"x":1493,"y":1432},"end":{"x":1498,"y":1334}},{"type":"L","x":1503,"y":1215},{"type":"L","x":1502,"y":1174},{"type":"L","x":1509,"y":906},{"type":"L","x":1512,"y":813}],"track":[{"x":1561,"y":287,"size":155},{"x":1590,"y":1307,"size":105},{"x":1637,"y":1722,"size":110},{"x":1412,"y":1502,"size":105}]},{"outline":[{"type":"M","x":1503,"y":1215},{"type":"Q","begin":{"x":1438,"y":1228},"end":{"x":1378,"y":1240}},{"type":"Q","begin":{"x":1318,"y":1252},"end":{"x":1273.5,"y":1259.5}},{"type":"Q","begin":{"x":1229,"y":1267},"end":{"x":1195,"y":1271}},{"type":"Q","begin":{"x":1161,"y":1275},"end":{"x":1150,"y":1273}},{"type":"L","x":1100,"y":1268},{"type":"L","x":1103,"y":1215},{"type":"L","x":1305,"y":1175},{"type":"Q","begin":{"x":1308,"y":1175},"end":{"x":1349,"y":1164.5}},{"type":"Q","begin":{"x":1390,"y":1154},"end":{"x":1414,"y":1153}},{"type":"Q","begin":{"x":1443,"y":1153},"end":{"x":1459,"y":1159}},{"type":"L","x":1502,"y":1174},{"type":"L","x":1503,"y":1215}],"track":[{"x":1113,"y":1239,"size":110},{"x":1492,"y":1188,"size":115}]},{"outline":[{"type":"M","x":1422,"y":1565},{"type":"Q","begin":{"x":1322,"y":1576},"end":{"x":1245.5,"y":1586}},{"type":"Q","begin":{"x":1169,"y":1596},"end":{"x":1156,"y":1596}},{"type":"L","x":1081,"y":1599},{"type":"L","x":1090,"y":1528},{"type":"L","x":1300,"y":1493},{"type":"L","x":1401,"y":1473},{"type":"Q","begin":{"x":1433,"y":1472},"end":{"x":1450,"y":1479}},{"type":"L","x":1422,"y":1565}],"track":[{"x":1090,"y":1563},{"x":1453,"y":1520}]}]