[{"outline":[{"type":"M","x":906,"y":576},{"type":"L","x":905,"y":364},{"type":"Q","begin":{"x":904,"y":302},"end":{"x":899.5,"y":268.5}},{"type":"Q","begin":{"x":895,"y":235},"end":{"x":888.5,"y":208}},{"type":"Q","begin":{"x":882,"y":181},"end":{"x":871.5,"y":159.5}},{"type":"Q","begin":{"x":861,"y":138},"end":{"x":857.5,"y":129}},{"type":"Q","begin":{"x":854,"y":120},"end":{"x":859,"y":110.5}},{"type":"Q","begin":{"x":864,"y":101},"end":{"x":882.5,"y":98.5}},{"type":"Q","begin":{"x":901,"y":96},"end":{"x":920,"y":97}},{"type":"Q","begin":{"x":939,"y":99},"end":{"x":962.5,"y":103.5}},{"type":"Q","begin":{"x":986,"y":108},"end":{"x":1007.5,"y":115}},{"type":"Q","begin":{"x":1029,"y":122},"end":{"x":1045,"y":134}},{"type":"Q","begin":{"x":1061,"y":146},"end":{"x":1061.5,"y":154}},{"type":"Q","begin":{"x":1062,"y":162},"end":{"x":1051,"y":180}},{"type":"Q","begin":{"x":1042,"y":194},"end":{"x":1036,"y":215}},{"type":"Q","begin":{"x":1030,"y":236},"end":{"x":1029,"y":253}},{"type":"L","x":1027,"y":287},{"type":"L","x":1024,"y":325},{"type":"L","x":1021,"y":389},{"type":"L","x":1013,"y":560},{"type":"Q","begin":{"x":959.5,"y":626},"end":{"x":906,"y":576}}],"track":[{"x":953,"y":109},{"x":961,"y":585}]},{"outline":[{"type":"M","x":1024,"y":325},{"type":"L","x":1227,"y":281},{"type":"Q","begin":{"x":1259,"y":275},"end":{"x":1282,"y":268.5}},{"type":"Q","begin":{"x":1305,"y":262},"end":{"x":1316,"y":261}},{"type":"Q","begin":{"x":1333,"y":261},"end":{"x":1361,"y":269}},{"type":"Q","begin":{"x":1389,"y":277},"end":{"x":1409.5,"y":295}},{"type":"Q","begin":{"x":1430,"y":313},"end":{"x":1428,"y":323}},{"type":"Q","begin":{"x":1426,"y":333},"end":{"x":1404.5,"y":342.5}},{"type":"Q","begin":{"x":1383,"y":352},"end":{"x":1344,"y":356}},{"type":"Q","begin":{"x":1305,"y":360},"end":{"x":1234.5,"y":371}},{"type":"Q","begin":{"x":1164,"y":382},"end":{"x":1122.5,"y":388}},{"type":"Q","begin":{"x":1081,"y":394},"end":{"x":1069,"y":392}},{"type":"L","x":1021,"y":389},{"type":"L","x":1024,"y":325}],"track":[{"x":1031,"y":357},{"x":1395,"y":287}]},{"outline":[{"type":"M","x":726,"y":1087},{"type":"L","x":709,"y":1115},{"type":"Q","begin":{"x":702,"y":1126},"end":{"x":691,"y":1128}},{"type":"Q","begin":{"x":680,"y":1130},"end":{"x":665,"y":1113}},{"type":"Q","begin":{"x":650,"y":1097},"end":{"x":644.5,"y":1074.5}},{"type":"Q","begin":{"x":639,"y":1052},"end":{"x":634,"y":1012}},{"type":"L","x":604,"y":776},{"type":"Q","begin":{"x":600,"y":747},"end":{"x":588,"y":707}},{"type":"Q","begin":{"x":576,"y":667},"end":{"x":557,"y":646}},{"type":"Q","begin":{"x":538,"y":625},"end":{"x":535.5,"y":613.5}},{"type":"Q","begin":{"x":533,"y":602},"end":{"x":543,"y":592}},{"type":"Q","begin":{"x":549,"y":586},"end":{"x":587,"y":592}},{"type":"L","x":640,"y":603},{"type":"Q","begin":{"x":688,"y":618.5},"end":{"x":690,"y":662}},{"type":"L","x":707,"y":823},{"type":"L","x":709,"y":876},{"type":"L","x":726,"y":1021},{"type":"L","x":726,"y":1087}],"track":[{"x":614,"y":603,"size":115},{"x":695,"y":1118}]},{"outline":[{"type":"M","x":640,"y":603},{"type":"L","x":906,"y":576},{"type":"L","x":1013,"y":560},{"type":"L","x":1208,"y":528},{"type":"L","x":1291,"y":515},{"type":"Q","begin":{"x":1361,"y":498},"end":{"x":1369,"y":498}},{"type":"Q","begin":{"x":1392,"y":499},"end":{"x":1415,"y":508}},{"type":"Q","begin":{"x":1438,"y":517},"end":{"x":1469,"y":536.5}},{"type":"Q","begin":{"x":1500,"y":556},"end":{"x":1517.5,"y":576.5}},{"type":"Q","begin":{"x":1535,"y":597},"end":{"x":1533,"y":612}},{"type":"Q","begin":{"x":1531,"y":620},"end":{"x":1515,"y":642}},{"type":"Q","begin":{"x":1499,"y":664},"end":{"x":1483,"y":707}},{"type":"L","x":1449,"y":801},{"type":"L","x":1374,"y":1007},{"type":"Q","begin":{"x":1351,"y":1069},"end":{"x":1329.5,"y":1095}},{"type":"Q","begin":{"x":1308,"y":1121},"end":{"x":1288,"y":1115.5}},{"type":"Q","begin":{"x":1268,"y":1110},"end":{"x":1258,"y":1093}},{"type":"L","x":1236,"y":1060},{"type":"Q","begin":{"x":1193.5,"y":972.5},"end":{"x":1261,"y":1001}},{"type":"Q","begin":{"x":1286,"y":923},"end":{"x":1291,"y":904}},{"type":"L","x":1310,"y":826},{"type":"L","x":1321,"y":778},{"type":"L","x":1338,"y":690},{"type":"Q","begin":{"x":1348,"y":637},"end":{"x":1340,"y":624}},{"type":"Q","begin":{"x":1332,"y":611},"end":{"x":1304,"y":604.5}},{"type":"Q","begin":{"x":1276,"y":598},"end":{"x":1227,"y":603}},{"type":"Q","begin":{"x":1175,"y":610},"end":{"x":1098,"y":617}},{"type":"Q","begin":{"x":1021,"y":624},"end":{"x":996,"y":626}},{"type":"L","x":690,"y":662},{"type":"L","x":640,"y":603}],"track":[{"x":664,"y":626,"size":95},{"x":1137,"y":546,"size":100},{"x":1402,"y":496,"size":85},{"x":1509,"y":563,"size":90},{"x":1387,"y":792,"size":100},{"x":1373,"y":1116,"size":110},{"x":1235,"y":1010,"size":75}]},{"outline":[{"type":"M","x":707,"y":823},{"type":"L","x":1010,"y":788},{"type":"L","x":1082,"y":776},{"type":"L","x":1163,"y":765},{"type":"Q","begin":{"x":1218,"y":756},"end":{"x":1233,"y":756}},{"type":"Q","begin":{"x":1262,"y":757},"end":{"x":1277,"y":762}},{"type":"L","x":1321,"y":778},{"type":"L","x":1310,"y":826},{"type":"L","x":986,"y":865},{"type":"L","x":854,"y":879},{"type":"Q","begin":{"x":798,"y":888},"end":{"x":790,"y":888}},{"type":"Q","begin":{"x":753,"y":891},"end":{"x":735,"y":884}},{"type":"L","x":709,"y":876},{"type":"L","x":707,"y":823}],"track":[{"x":716,"y":851,"size":105},{"x":1306,"y":793,"size":110}]},{"outline":[{"type":"M","x":902,"y":1079},{"type":"Q","begin":{"x":880,"y":1082},"end":{"x":843.5,"y":1085}},{"type":"Q","begin":{"x":807,"y":1088},"end":{"x":777,"y":1087}},{"type":"L","x":726,"y":1087},{"type":"L","x":726,"y":1021},{"type":"L","x":1035,"y":996},{"type":"L","x":1174,"y":982},{"type":"Q","begin":{"x":1208,"y":983},"end":{"x":1221,"y":987}},{"type":"L","x":1261,"y":1001},{"type":"L","x":1236,"y":1060},{"type":"Q","begin":{"x":1133,"y":1062},"end":{"x":1082,"y":1065}},{"type":"L","x":1045,"y":1068},{"type":"L","x":981,"y":1072},{"type":"L","x":902,"y":1079}],"track":[{"x":738,"y":1056,"size":110},{"x":1246,"y":1024,"size":110}]},{"outline":[{"type":"M","x":936,"y":1335},{"type":"Q","begin":{"x":873,"y":1340},"end":{"x":837,"y":1344}},{"type":"Q","begin":{"x":801,"y":1348},"end":{"x":737,"y":1355}},{"type":"L","x":623,"y":1369},{"type":"Q","begin":{"x":598,"y":1373},"end":{"x":554.5,"y":1381}},{"type":"Q","begin":{"x":511,"y":1389},"end":{"x":478.5,"y":1398}},{"type":"Q","begin":{"x":446,"y":1407},"end":{"x":434.5,"y":1409}},{"type":"Q","begin":{"x":423,"y":1411},"end":{"x":412,"y":1410}},{"type":"Q","begin":{"x":393,"y":1410},"end":{"x":373.5,"y":1403}},{"type":"Q","begin":{"x":354,"y":1396},"end":{"x":332.5,"y":1383.5}},{"type":"Q","begin":{"x":311,"y":1371},"end":{"x":291.5,"y":1356.5}},{"type":"Q","begin":{"x":272,"y":1342},"end":{"x":269.5,"y":1331.5}},{"type":"Q","begin":{"x":267,"y":1321},"end":{"x":271,"y":1315.5}},{"type":"Q","begin":{"x":275,"y":1310},"end":{"x":297,"y":1308}},{"type":"L","x":350,"y":1304},{"type":"Q","begin":{"x":352,"y":1304},"end":{"x":431.5,"y":1301}},{"type":"Q","begin":{"x":511,"y":1298},"end":{"x":617,"y":1286.5}},{"type":"Q","begin":{"x":723,"y":1275},"end":{"x":726,"y":1274}},{"type":"L","x":932,"y":1255},{"type":"L","x":1044,"y":1247},{"type":"L","x":1225,"y":1235},{"type":"Q","begin":{"x":1282,"y":1232},"end":{"x":1332,"y":1226.5}},{"type":"Q","begin":{"x":1382,"y":1221},"end":{"x":1451,"y":1212}},{"type":"Q","begin":{"x":1520,"y":1203},"end":{"x":1554,"y":1195.5}},{"type":"Q","begin":{"x":1588,"y":1188},"end":{"x":1601,"y":1187}},{"type":"Q","begin":{"x":1622,"y":1187},"end":{"x":1646,"y":1193.5}},{"type":"Q","begin":{"x":1670,"y":1200},"end":{"x":1714.5,"y":1220.5}},{"type":"Q","begin":{"x":1759,"y":1241},"end":{"x":1771.5,"y":1260}},{"type":"Q","begin":{"x":1784,"y":1279},"end":{"x":1777.5,"y":1292}},{"type":"Q","begin":{"x":1771,"y":1305},"end":{"x":1747.5,"y":1310}},{"type":"Q","begin":{"x":1724,"y":1315},"end":{"x":1681,"y":1313}},{"type":"L","x":1529,"y":1309},{"type":"Q","begin":{"x":1493,"y":1309},"end":{"x":1353,"y":1315}},{"type":"L","x":1172,"y":1321},{"type":"L","x":1039,"y":1326},{"type":"L","x":936,"y":1335}],"track":[{"x":320,"y":1365},{"x":951,"y":1299},{"x":1727,"y":1240}]},{"outline":[{"type":"M","x":1039,"y":1326},{"type":"L","x":1037,"y":1456},{"type":"L","x":1039,"y":1729},{"type":"Q","begin":{"x":1039,"y":1814},"end":{"x":1036.5,"y":1831.5}},{"type":"Q","begin":{"x":1034,"y":1849},"end":{"x":1029.5,"y":1863.5}},{"type":"Q","begin":{"x":1025,"y":1878},"end":{"x":1013.5,"y":1901.5}},{"type":"Q","begin":{"x":1002,"y":1925},"end":{"x":990.5,"y":1938.5}},{"type":"Q","begin":{"x":979,"y":1952},"end":{"x":970.5,"y":1953.5}},{"type":"Q","begin":{"x":962,"y":1955},"end":{"x":950,"y":1940}},{"type":"Q","begin":{"x":941,"y":1930},"end":{"x":931.5,"y":1908.5}},{"type":"Q","begin":{"x":922,"y":1887},"end":{"x":915,"y":1868.5}},{"type":"Q","begin":{"x":908,"y":1850},"end":{"x":901,"y":1823}},{"type":"Q","begin":{"x":894,"y":1796},"end":{"x":893.5,"y":1778}},{"type":"Q","begin":{"x":893,"y":1760},"end":{"x":903,"y":1718}},{"type":"Q","begin":{"x":912,"y":1675},"end":{"x":919,"y":1624}},{"type":"Q","begin":{"x":926,"y":1573},"end":{"x":928.5,"y":1535.5}},{"type":"Q","begin":{"x":931,"y":1498},"end":{"x":933,"y":1452}},{"type":"L","x":936,"y":1335},{"type":"L","x":932,"y":1255},{"type":"L","x":932,"y":1219},{"type":"Q","begin":{"x":932,"y":1187},"end":{"x":926.5,"y":1163.5}},{"type":"Q","begin":{"x":921,"y":1140},"end":{"x":910.5,"y":1116.5}},{"type":"Q","begin":{"x":900,"y":1093},"end":{"x":901,"y":1088}},{"type":"L","x":902,"y":1079},{"type":"L","x":981,"y":1072},{"type":"Q","begin":{"x":1005,"y":1080},"end":{"x":1021.5,"y":1086.5}},{"type":"Q","begin":{"x":1038,"y":1093},"end":{"x":1053.5,"y":1106}},{"type":"Q","begin":{"x":1069,"y":1119},"end":{"x":1070.5,"y":1130.5}},{"type":"Q","begin":{"x":1072,"y":1142},"end":{"x":1061.5,"y":1166}},{"type":"Q","begin":{"x":1051,"y":1190},"end":{"x":1049,"y":1210}},{"type":"L","x":1044,"y":1247},{"type":"L","x":1039,"y":1326}],"track":[{"x":989,"y":1085,"size":140},{"x":979,"y":1475},{"x":970,"y":1925}]},{"outline":[{"type":"M","x":366,"y":1809},{"type":"L","x":393,"y":1790},{"type":"Q","begin":{"x":421,"y":1770},"end":{"x":469.5,"y":1728}},{"type":"Q","begin":{"x":518,"y":1686},"end":{"x":560.5,"y":1643}},{"type":"Q","begin":{"x":603,"y":1600},"end":{"x":631.5,"y":1559}},{"type":"Q","begin":{"x":660,"y":1518},"end":{"x":664.5,"y":1491.5}},{"type":"Q","begin":{"x":669,"y":1465},"end":{"x":675,"y":1459.5}},{"type":"Q","begin":{"x":681,"y":1454},"end":{"x":699,"y":1456}},{"type":"Q","begin":{"x":721,"y":1459},"end":{"x":748,"y":1479}},{"type":"Q","begin":{"x":775,"y":1499},"end":{"x":792,"y":1524.5}},{"type":"Q","begin":{"x":809,"y":1550},"end":{"x":802,"y":1563}},{"type":"Q","begin":{"x":799,"y":1568},"end":{"x":779.5,"y":1579}},{"type":"Q","begin":{"x":760,"y":1590},"end":{"x":726,"y":1625}},{"type":"Q","begin":{"x":692,"y":1660},"end":{"x":653,"y":1693.5}},{"type":"Q","begin":{"x":614,"y":1727},"end":{"x":567,"y":1758.5}},{"type":"Q","begin":{"x":520,"y":1790},"end":{"x":482,"y":1808}},{"type":"Q","begin":{"x":444,"y":1826},"end":{"x":404,"y":1839}},{"type":"L","x":359,"y":1854},{"type":"Q","begin":{"x":328,"y":1865},"end":{"x":323,"y":1857.5}},{"type":"Q","begin":{"x":318,"y":1850},"end":{"x":323,"y":1837}},{"type":"L","x":366,"y":1809}],"track":[{"x":761,"y":1499},{"x":571,"y":1704},{"x":329,"y":1848}]},{"outline":[{"type":"M","x":1223,"y":1495},{"type":"L","x":1195,"y":1467},{"type":"Q","begin":{"x":1183,"y":1456},"end":{"x":1187,"y":1448}},{"type":"Q","begin":{"x":1191,"y":1440},"end":{"x":1198.5,"y":1440.5}},{"type":"Q","begin":{"x":1206,"y":1441},"end":{"x":1225,"y":1447}},{"type":"L","x":1265,"y":1462},{"type":"Q","begin":{"x":1289,"y":1472},"end":{"x":1330.5,"y":1491.5}},{"type":"Q","begin":{"x":1372,"y":1511},"end":{"x":1408,"y":1532.5}},{"type":"Q","begin":{"x":1444,"y":1554},"end":{"x":1486,"y":1586.5}},{"type":"Q","begin":{"x":1528,"y":1619},"end":{"x":1555,"y":1649.5}},{"type":"Q","begin":{"x":1582,"y":1680},"end":{"x":1593,"y":1708.5}},{"type":"Q","begin":{"x":1604,"y":1737},"end":{"x":1608.5,"y":1773.5}},{"type":"Q","begin":{"x":1613,"y":1810},"end":{"x":1603.5,"y":1833}},{"type":"Q","begin":{"x":1594,"y":1856},"end":{"x":1578.5,"y":1860}},{"type":"Q","begin":{"x":1563,"y":1864},"end":{"x":1542,"y":1852}},{"type":"Q","begin":{"x":1527,"y":1844},"end":{"x":1508.5,"y":1827}},{"type":"Q","begin":{"x":1490,"y":1810},"end":{"x":1452,"y":1766}},{"type":"Q","begin":{"x":1414,"y":1722},"end":{"x":1386,"y":1686}},{"type":"L","x":1324,"y":1608},{"type":"Q","begin":{"x":1289,"y":1565},"end":{"x":1270.5,"y":1545}},{"type":"Q","begin":{"x":1252,"y":1525},"end":{"x":1223,"y":1495}}],"track":[{"x":1196,"y":1452,"size":105},{"x":1596,"y":1826}]}]