[{"outline":[{"type":"M","x":496,"y":812},{"type":"L","x":348,"y":837},{"type":"Q","begin":{"x":316,"y":843},"end":{"x":292.5,"y":844}},{"type":"Q","begin":{"x":269,"y":845},"end":{"x":234.5,"y":838}},{"type":"Q","begin":{"x":200,"y":831},"end":{"x":183.5,"y":814.5}},{"type":"Q","begin":{"x":167,"y":798},"end":{"x":172,"y":788.5}},{"type":"Q","begin":{"x":177,"y":779},"end":{"x":201,"y":776}},{"type":"L","x":252,"y":771},{"type":"Q","begin":{"x":261,"y":771},"end":{"x":285,"y":765}},{"type":"L","x":410,"y":743},{"type":"L","x":508,"y":723},{"type":"L","x":593,"y":707},{"type":"Q","begin":{"x":618,"y":699},"end":{"x":640.5,"y":692.5}},{"type":"Q","begin":{"x":663,"y":686},"end":{"x":680.5,"y":680.5}},{"type":"Q","begin":{"x":698,"y":675},"end":{"x":708,"y":673}},{"type":"Q","begin":{"x":731,"y":671},"end":{"x":765.5,"y":683.5}},{"type":"Q","begin":{"x":800,"y":696},"end":{"x":809.5,"y":711}},{"type":"Q","begin":{"x":819,"y":726},"end":{"x":817,"y":736}},{"type":"Q","begin":{"x":813,"y":747},"end":{"x":779,"y":758}},{"type":"Q","begin":{"x":745,"y":769},"end":{"x":727,"y":773}},{"type":"L","x":652,"y":787},{"type":"L","x":588,"y":801},{"type":"L","x":496,"y":812}],"track":[{"x":191,"y":802,"size":80},{"x":794,"y":713,"size":90}]},{"outline":[{"type":"M","x":508,"y":723},{"type":"L","x":508,"y":553},{"type":"Q","begin":{"x":508,"y":529},"end":{"x":504,"y":465}},{"type":"Q","begin":{"x":500,"y":401},"end":{"x":498,"y":377}},{"type":"Q","begin":{"x":496,"y":353},"end":{"x":490,"y":322}},{"type":"Q","begin":{"x":484,"y":291},"end":{"x":473,"y":269.5}},{"type":"Q","begin":{"x":462,"y":248},"end":{"x":462.5,"y":239.5}},{"type":"Q","begin":{"x":463,"y":231},"end":{"x":470.5,"y":223}},{"type":"Q","begin":{"x":478,"y":215},"end":{"x":508,"y":223}},{"type":"Q","begin":{"x":535,"y":231},"end":{"x":567,"y":249}},{"type":"Q","begin":{"x":599,"y":267},"end":{"x":616,"y":281.5}},{"type":"Q","begin":{"x":633,"y":296},"end":{"x":635,"y":308}},{"type":"Q","begin":{"x":637,"y":320},"end":{"x":624,"y":359}},{"type":"Q","begin":{"x":617,"y":378},"end":{"x":614,"y":424}},{"type":"L","x":605,"y":519},{"type":"L","x":600,"y":615},{"type":"L","x":593,"y":707},{"type":"L","x":588,"y":801},{"type":"L","x":580,"y":973},{"type":"L","x":580,"y":1007},{"type":"L","x":572,"y":1558},{"type":"L","x":572,"y":1751},{"type":"Q","begin":{"x":569,"y":1774},"end":{"x":565,"y":1791}},{"type":"Q","begin":{"x":561,"y":1808},"end":{"x":551,"y":1833.5}},{"type":"Q","begin":{"x":541,"y":1859},"end":{"x":530.5,"y":1875.5}},{"type":"Q","begin":{"x":520,"y":1892},"end":{"x":508.5,"y":1894}},{"type":"Q","begin":{"x":497,"y":1896},"end":{"x":476,"y":1862}},{"type":"Q","begin":{"x":460,"y":1839},"end":{"x":453.5,"y":1819}},{"type":"Q","begin":{"x":447,"y":1799},"end":{"x":439,"y":1763.5}},{"type":"Q","begin":{"x":431,"y":1728},"end":{"x":435,"y":1705}},{"type":"Q","begin":{"x":435,"y":1701},"end":{"x":442.5,"y":1678}},{"type":"Q","begin":{"x":450,"y":1655},"end":{"x":460,"y":1608}},{"type":"Q","begin":{"x":470,"y":1561},"end":{"x":475,"y":1529.5}},{"type":"Q","begin":{"x":480,"y":1498},"end":{"x":485,"y":1380}},{"type":"L","x":499,"y":1040},{"type":"L","x":508,"y":723}],"track":[{"x":565,"y":267},{"x":551,"y":1026},{"x":509,"y":1877,"size":115}]},{"outline":[{"type":"M","x":499,"y":1040},{"type":"Q","begin":{"x":480,"y":1071},"end":{"x":458.5,"y":1106}},{"type":"Q","begin":{"x":437,"y":1141},"end":{"x":390,"y":1204.5}},{"type":"Q","begin":{"x":343,"y":1268},"end":{"x":293,"y":1320}},{"type":"Q","begin":{"x":243,"y":1372},"end":{"x":201,"y":1402.5}},{"type":"Q","begin":{"x":159,"y":1433},"end":{"x":126,"y":1452}},{"type":"L","x":107,"y":1463},{"type":"Q","begin":{"x":90,"y":1473},"end":{"x":86,"y":1465}},{"type":"Q","begin":{"x":82,"y":1457},"end":{"x":90,"y":1447}},{"type":"L","x":115,"y":1421},{"type":"Q","begin":{"x":149,"y":1386},"end":{"x":172.5,"y":1360}},{"type":"Q","begin":{"x":196,"y":1334},"end":{"x":243,"y":1272.5}},{"type":"Q","begin":{"x":290,"y":1211},"end":{"x":327,"y":1151.5}},{"type":"Q","begin":{"x":364,"y":1092},"end":{"x":413,"y":1004}},{"type":"Q","begin":{"x":462,"y":916},"end":{"x":474,"y":879}},{"type":"L","x":496,"y":812},{"type":"Q","begin":{"x":574.5,"y":768},"end":{"x":499,"y":1040}}],"track":[{"x":507,"y":898},{"x":322,"y":1226},{"x":96,"y":1461}]},{"outline":[{"type":"M","x":580,"y":973},{"type":"Q","begin":{"x":607,"y":980},"end":{"x":635,"y":985.5}},{"type":"Q","begin":{"x":663,"y":991},"end":{"x":691.5,"y":998.5}},{"type":"Q","begin":{"x":720,"y":1006},"end":{"x":742.5,"y":1025}},{"type":"Q","begin":{"x":765,"y":1044},"end":{"x":771.5,"y":1060.5}},{"type":"Q","begin":{"x":778,"y":1077},"end":{"x":780,"y":1098.5}},{"type":"Q","begin":{"x":782,"y":1120},"end":{"x":772.5,"y":1138.5}},{"type":"Q","begin":{"x":763,"y":1157},"end":{"x":746,"y":1161}},{"type":"Q","begin":{"x":729,"y":1165},"end":{"x":708,"y":1151}},{"type":"Q","begin":{"x":694,"y":1143},"end":{"x":677,"y":1122}},{"type":"L","x":648,"y":1087},{"type":"L","x":580,"y":1007},{"type":"L","x":580,"y":973}],"track":[{"x":591,"y":991,"size":95},{"x":761,"y":1136,"size":100}]},{"outline":[{"type":"M","x":925,"y":276},{"type":"L","x":913,"y":261},{"type":"Q","begin":{"x":904,"y":250},"end":{"x":908,"y":241.5}},{"type":"Q","begin":{"x":912,"y":233},"end":{"x":930,"y":236}},{"type":"L","x":964,"y":242},{"type":"Q","begin":{"x":993,"y":248},"end":{"x":1023.5,"y":256.5}},{"type":"Q","begin":{"x":1054,"y":265},"end":{"x":1074,"y":280.5}},{"type":"Q","begin":{"x":1094,"y":296},"end":{"x":1106,"y":317.5}},{"type":"Q","begin":{"x":1118,"y":339},"end":{"x":1112,"y":370}},{"type":"Q","begin":{"x":1106,"y":401},"end":{"x":1089,"y":415}},{"type":"Q","begin":{"x":1072,"y":429},"end":{"x":1042,"y":417}},{"type":"Q","begin":{"x":1025,"y":411},"end":{"x":1004,"y":383}},{"type":"L","x":975,"y":345},{"type":"Q","begin":{"x":952,"y":317},"end":{"x":938.5,"y":297}},{"type":"Q","begin":{"x":925,"y":277},"end":{"x":925,"y":276}}],"track":[{"x":918,"y":247,"size":95},{"x":1090,"y":393,"size":100}]},{"outline":[{"type":"M","x":1250,"y":411},{"type":"L","x":1222,"y":425},{"type":"Q","begin":{"x":1213,"y":430},"end":{"x":1208,"y":423.5}},{"type":"Q","begin":{"x":1203,"y":417},"end":{"x":1214,"y":406}},{"type":"L","x":1233,"y":387},{"type":"Q","begin":{"x":1238,"y":382},"end":{"x":1276,"y":337.5}},{"type":"Q","begin":{"x":1314,"y":293},"end":{"x":1317,"y":289}},{"type":"L","x":1350,"y":239},{"type":"Q","begin":{"x":1373,"y":205},"end":{"x":1381,"y":180.5}},{"type":"Q","begin":{"x":1389,"y":156},"end":{"x":1393.5,"y":150.5}},{"type":"Q","begin":{"x":1398,"y":145},"end":{"x":1407,"y":142}},{"type":"Q","begin":{"x":1416,"y":139},"end":{"x":1442,"y":155}},{"type":"L","x":1481,"y":180},{"type":"Q","begin":{"x":1503,"y":197},"end":{"x":1521.5,"y":219.5}},{"type":"Q","begin":{"x":1540,"y":242},"end":{"x":1537,"y":253}},{"type":"Q","begin":{"x":1534,"y":263},"end":{"x":1520,"y":270}},{"type":"L","x":1489,"y":281},{"type":"Q","begin":{"x":1474,"y":287},"end":{"x":1434,"y":314.5}},{"type":"Q","begin":{"x":1394,"y":342},"end":{"x":1331,"y":372}},{"type":"L","x":1250,"y":411}],"track":[{"x":1478,"y":188,"size":110},{"x":1221,"y":420,"size":80}]},{"outline":[{"type":"M","x":1136,"y":534},{"type":"Q","begin":{"x":1097,"y":540},"end":{"x":1078,"y":542}},{"type":"L","x":1025,"y":547},{"type":"Q","begin":{"x":961,"y":554},"end":{"x":942,"y":552}},{"type":"L","x":897,"y":545},{"type":"Q","begin":{"x":869,"y":542},"end":{"x":856,"y":532}},{"type":"Q","begin":{"x":843,"y":522},"end":{"x":847,"y":509}},{"type":"Q","begin":{"x":849,"y":500},"end":{"x":858.5,"y":497.5}},{"type":"Q","begin":{"x":868,"y":495},"end":{"x":892,"y":492}},{"type":"L","x":922,"y":489},{"type":"L","x":981,"y":484},{"type":"Q","begin":{"x":995,"y":483},"end":{"x":1075,"y":470}},{"type":"L","x":1201,"y":451},{"type":"L","x":1331,"y":425},{"type":"Q","begin":{"x":1384,"y":416},"end":{"x":1417,"y":404.5}},{"type":"Q","begin":{"x":1450,"y":393},"end":{"x":1459,"y":392}},{"type":"Q","begin":{"x":1471,"y":392},"end":{"x":1488.5,"y":396}},{"type":"Q","begin":{"x":1506,"y":400},"end":{"x":1533,"y":410.5}},{"type":"Q","begin":{"x":1560,"y":421},"end":{"x":1568,"y":432}},{"type":"Q","begin":{"x":1576,"y":443},"end":{"x":1574,"y":451}},{"type":"Q","begin":{"x":1571,"y":460},"end":{"x":1552.5,"y":466.5}},{"type":"Q","begin":{"x":1534,"y":473},"end":{"x":1513,"y":477}},{"type":"L","x":1380,"y":503},{"type":"L","x":1253,"y":526},{"type":"L","x":1136,"y":534}],"track":[{"x":861,"y":515,"size":100},{"x":1542,"y":421}]},{"outline":[{"type":"M","x":1137,"y":719},{"type":"Q","begin":{"x":1095,"y":726},"end":{"x":1067,"y":729.5}},{"type":"Q","begin":{"x":1039,"y":733},"end":{"x":1018,"y":733.5}},{"type":"Q","begin":{"x":997,"y":734},"end":{"x":986,"y":733}},{"type":"Q","begin":{"x":955,"y":733},"end":{"x":931,"y":727}},{"type":"Q","begin":{"x":907,"y":721},"end":{"x":901.5,"y":713}},{"type":"Q","begin":{"x":896,"y":705},"end":{"x":897,"y":700}},{"type":"Q","begin":{"x":897,"y":691},"end":{"x":917,"y":684}},{"type":"L","x":958,"y":679},{"type":"L","x":1136,"y":656},{"type":"L","x":1248,"y":632},{"type":"Q","begin":{"x":1303,"y":620},"end":{"x":1330.5,"y":612.5}},{"type":"Q","begin":{"x":1358,"y":605},"end":{"x":1370,"y":604}},{"type":"Q","begin":{"x":1382,"y":604},"end":{"x":1414,"y":610.5}},{"type":"Q","begin":{"x":1446,"y":617},"end":{"x":1466,"y":627.5}},{"type":"Q","begin":{"x":1486,"y":638},"end":{"x":1486.5,"y":648}},{"type":"Q","begin":{"x":1487,"y":658},"end":{"x":1477.5,"y":665.5}},{"type":"Q","begin":{"x":1468,"y":673},"end":{"x":1422,"y":680}},{"type":"L","x":1244,"y":707},{"type":"L","x":1137,"y":719}],"track":[{"x":907,"y":703},{"x":1460,"y":633}]},{"outline":[{"type":"M","x":1136,"y":656},{"type":"L","x":1136,"y":534},{"type":"L","x":1253,"y":526},{"type":"L","x":1248,"y":632},{"type":"L","x":1244,"y":707},{"type":"L","x":1241,"y":818},{"type":"Q","begin":{"x":1186,"y":871.5},"end":{"x":1131,"y":831}},{"type":"L","x":1137,"y":719},{"type":"L","x":1136,"y":656}],"track":[{"x":1196,"y":541,"size":105},{"x":1188,"y":840,"size":115}]},{"outline":[{"type":"M","x":1241,"y":818},{"type":"L","x":1376,"y":798},{"type":"L","x":1484,"y":779},{"type":"Q","begin":{"x":1542,"y":769},"end":{"x":1569,"y":762.5}},{"type":"Q","begin":{"x":1596,"y":756},"end":{"x":1609,"y":756}},{"type":"Q","begin":{"x":1630,"y":757},"end":{"x":1663.5,"y":772}},{"type":"Q","begin":{"x":1697,"y":787},"end":{"x":1721,"y":807}},{"type":"Q","begin":{"x":1745,"y":827},"end":{"x":1738,"y":838.5}},{"type":"Q","begin":{"x":1731,"y":850},"end":{"x":1715,"y":851}},{"type":"L","x":1645,"y":856},{"type":"L","x":1517,"y":862},{"type":"Q","begin":{"x":1467,"y":865},"end":{"x":1295,"y":883}},{"type":"Q","begin":{"x":1123,"y":901},"end":{"x":1068.5,"y":909}},{"type":"Q","begin":{"x":1014,"y":917},"end":{"x":975.5,"y":928.5}},{"type":"Q","begin":{"x":937,"y":940},"end":{"x":925,"y":940}},{"type":"Q","begin":{"x":903,"y":941},"end":{"x":872.5,"y":931.5}},{"type":"Q","begin":{"x":842,"y":922},"end":{"x":823,"y":912}},{"type":"Q","begin":{"x":804,"y":902},"end":{"x":802,"y":895.5}},{"type":"Q","begin":{"x":800,"y":889},"end":{"x":802,"y":883}},{"type":"Q","begin":{"x":804,"y":877},"end":{"x":819,"y":873}},{"type":"L","x":869,"y":868},{"type":"L","x":930,"y":860},{"type":"Q","begin":{"x":1052,"y":844},"end":{"x":1058,"y":843}},{"type":"L","x":1131,"y":831},{"type":"L","x":1241,"y":818}],"track":[{"x":842,"y":913},{"x":1220,"y":861},{"x":1676,"y":786}]},{"outline":[{"type":"M","x":1086,"y":971},{"type":"L","x":1078,"y":959},{"type":"Q","begin":{"x":1058,"y":929},"end":{"x":1059,"y":926.5}},{"type":"Q","begin":{"x":1060,"y":924},"end":{"x":1086,"y":923}},{"type":"Q","begin":{"x":1114,"y":923},"end":{"x":1146.5,"y":927}},{"type":"Q","begin":{"x":1179,"y":931},"end":{"x":1212,"y":940.5}},{"type":"Q","begin":{"x":1245,"y":950},"end":{"x":1258.5,"y":965.5}},{"type":"Q","begin":{"x":1272,"y":981},"end":{"x":1274.5,"y":1004}},{"type":"Q","begin":{"x":1277,"y":1027},"end":{"x":1267.5,"y":1042}},{"type":"Q","begin":{"x":1258,"y":1057},"end":{"x":1239.5,"y":1065}},{"type":"Q","begin":{"x":1221,"y":1073},"end":{"x":1189,"y":1059}},{"type":"Q","begin":{"x":1170,"y":1052},"end":{"x":1156,"y":1040}},{"type":"Q","begin":{"x":1142,"y":1028},"end":{"x":1117,"y":1005}},{"type":"Q","begin":{"x":1092,"y":982},"end":{"x":1086,"y":971}}],"track":[{"x":1072,"y":933,"size":100},{"x":1254,"y":1033,"size":95}]},{"outline":[{"type":"M","x":1275,"y":1328},{"type":"L","x":1278,"y":1583},{"type":"Q","begin":{"x":1278,"y":1643},"end":{"x":1271,"y":1698}},{"type":"Q","begin":{"x":1264,"y":1753},"end":{"x":1256.5,"y":1781.5}},{"type":"Q","begin":{"x":1249,"y":1810},"end":{"x":1231,"y":1840.5}},{"type":"Q","begin":{"x":1213,"y":1871},"end":{"x":1188,"y":1889.5}},{"type":"Q","begin":{"x":1163,"y":1908},"end":{"x":1153,"y":1907}},{"type":"Q","begin":{"x":1138,"y":1907},"end":{"x":1116,"y":1875}},{"type":"Q","begin":{"x":1094,"y":1843},"end":{"x":1085.5,"y":1832}},{"type":"Q","begin":{"x":1077,"y":1821},"end":{"x":1048.5,"y":1790.5}},{"type":"Q","begin":{"x":1020,"y":1760},"end":{"x":1000,"y":1743}},{"type":"L","x":975,"y":1723},{"type":"Q","begin":{"x":958,"y":1710},"end":{"x":963.5,"y":1701.5}},{"type":"Q","begin":{"x":969,"y":1693},"end":{"x":997,"y":1698}},{"type":"L","x":1025,"y":1704},{"type":"Q","begin":{"x":1034,"y":1707},"end":{"x":1058,"y":1711}},{"type":"Q","begin":{"x":1082,"y":1715},"end":{"x":1102.5,"y":1720}},{"type":"Q","begin":{"x":1123,"y":1725},"end":{"x":1133,"y":1721}},{"type":"Q","begin":{"x":1147,"y":1716},"end":{"x":1157,"y":1694.5}},{"type":"Q","begin":{"x":1167,"y":1673},"end":{"x":1169,"y":1643}},{"type":"L","x":1179,"y":1425},{"type":"Q","begin":{"x":1182,"y":1344},"end":{"x":1181,"y":1319}},{"type":"L","x":1175,"y":1238},{"type":"Q","begin":{"x":1175,"y":1221},"end":{"x":1171,"y":1211}},{"type":"Q","begin":{"x":1167,"y":1201},"end":{"x":1157,"y":1198.5}},{"type":"Q","begin":{"x":1147,"y":1196},"end":{"x":1105,"y":1202}},{"type":"L","x":1053,"y":1210},{"type":"L","x":992,"y":1221},{"type":"Q","begin":{"x":970,"y":1223},"end":{"x":947,"y":1217.5}},{"type":"Q","begin":{"x":924,"y":1212},"end":{"x":914.5,"y":1203}},{"type":"Q","begin":{"x":905,"y":1194},"end":{"x":907.5,"y":1186}},{"type":"Q","begin":{"x":910,"y":1178},"end":{"x":930,"y":1174}},{"type":"L","x":960,"y":1168},{"type":"Q","begin":{"x":975,"y":1165},"end":{"x":1020.5,"y":1153.5}},{"type":"Q","begin":{"x":1066,"y":1142},"end":{"x":1092,"y":1133.5}},{"type":"Q","begin":{"x":1118,"y":1125},"end":{"x":1144.5,"y":1110.5}},{"type":"Q","begin":{"x":1171,"y":1096},"end":{"x":1181,"y":1093}},{"type":"Q","begin":{"x":1197,"y":1090},"end":{"x":1215.5,"y":1095.5}},{"type":"Q","begin":{"x":1234,"y":1101},"end":{"x":1261,"y":1113.5}},{"type":"Q","begin":{"x":1288,"y":1126},"end":{"x":1300.5,"y":1136}},{"type":"Q","begin":{"x":1313,"y":1146},"end":{"x":1313.5,"y":1153}},{"type":"Q","begin":{"x":1314,"y":1160},"end":{"x":1297,"y":1193}},{"type":"Q","begin":{"x":1294,"y":1199},"end":{"x":1289,"y":1224}},{"type":"L","x":1281,"y":1266},{"type":"L","x":1275,"y":1328}],"track":[{"x":907,"y":1178,"size":80},{"x":1223,"y":1043,"size":60},{"x":1317,"y":1083,"size":60},{"x":1230,"y":1295,"size":90},{"x":1235,"y":1909,"size":105},{"x":974,"y":1706,"size":85}]},{"outline":[{"type":"M","x":922,"y":1391},{"type":"L","x":880,"y":1404},{"type":"L","x":853,"y":1415},{"type":"Q","begin":{"x":837,"y":1420},"end":{"x":817,"y":1415}},{"type":"Q","begin":{"x":802,"y":1412},"end":{"x":785.5,"y":1404.5}},{"type":"Q","begin":{"x":769,"y":1397},"end":{"x":758,"y":1384}},{"type":"Q","begin":{"x":747,"y":1371},"end":{"x":751,"y":1364}},{"type":"Q","begin":{"x":755,"y":1357},"end":{"x":766,"y":1355}},{"type":"L","x":805,"y":1349},{"type":"L","x":872,"y":1341},{"type":"Q","begin":{"x":872,"y":1341},"end":{"x":921,"y":1329.5}},{"type":"Q","begin":{"x":970,"y":1318},"end":{"x":989,"y":1310}},{"type":"Q","begin":{"x":1008,"y":1302},"end":{"x":1016,"y":1302}},{"type":"Q","begin":{"x":1029,"y":1303},"end":{"x":1050,"y":1316}},{"type":"Q","begin":{"x":1071,"y":1329},"end":{"x":1096.5,"y":1354.5}},{"type":"Q","begin":{"x":1122,"y":1380},"end":{"x":1116,"y":1394}},{"type":"Q","begin":{"x":1113,"y":1401},"end":{"x":1095,"y":1414}},{"type":"Q","begin":{"x":1077,"y":1427},"end":{"x":1067,"y":1437}},{"type":"Q","begin":{"x":1057,"y":1447},"end":{"x":1027,"y":1491}},{"type":"Q","begin":{"x":997,"y":1535},"end":{"x":959,"y":1576.5}},{"type":"Q","begin":{"x":921,"y":1618},"end":{"x":878.5,"y":1649}},{"type":"Q","begin":{"x":836,"y":1680},"end":{"x":795.5,"y":1701.5}},{"type":"Q","begin":{"x":755,"y":1723},"end":{"x":736,"y":1729}},{"type":"L","x":702,"y":1740},{"type":"Q","begin":{"x":679,"y":1748},"end":{"x":674.5,"y":1737.5}},{"type":"Q","begin":{"x":670,"y":1727},"end":{"x":694,"y":1710}},{"type":"L","x":719,"y":1693},{"type":"Q","begin":{"x":730,"y":1686},"end":{"x":767.5,"y":1651}},{"type":"Q","begin":{"x":805,"y":1616},"end":{"x":834,"y":1586}},{"type":"Q","begin":{"x":863,"y":1556},"end":{"x":891.5,"y":1514}},{"type":"Q","begin":{"x":920,"y":1472},"end":{"x":939.5,"y":1433}},{"type":"Q","begin":{"x":959,"y":1394},"end":{"x":951,"y":1389.5}},{"type":"Q","begin":{"x":943,"y":1385},"end":{"x":922,"y":1391}}],"track":[{"x":755,"y":1341,"size":55},{"x":1035,"y":1213,"size":50},{"x":1172,"y":1317,"size":65},{"x":969,"y":1494,"size":90},{"x":683,"y":1732,"size":80}]},{"outline":[{"type":"M","x":1367,"y":1327},{"type":"Q","begin":{"x":1409,"y":1288},"end":{"x":1427.5,"y":1268}},{"type":"Q","begin":{"x":1446,"y":1248},"end":{"x":1479.5,"y":1203.5}},{"type":"Q","begin":{"x":1513,"y":1159},"end":{"x":1522.5,"y":1146.5}},{"type":"Q","begin":{"x":1532,"y":1134},"end":{"x":1538,"y":1112.5}},{"type":"Q","begin":{"x":1544,"y":1091},"end":{"x":1550,"y":1085}},{"type":"Q","begin":{"x":1556,"y":1079},"end":{"x":1568,"y":1079}},{"type":"Q","begin":{"x":1575,"y":1080},"end":{"x":1595,"y":1091.5}},{"type":"Q","begin":{"x":1615,"y":1103},"end":{"x":1639,"y":1121}},{"type":"Q","begin":{"x":1663,"y":1139},"end":{"x":1682.5,"y":1162.5}},{"type":"Q","begin":{"x":1702,"y":1186},"end":{"x":1696,"y":1199}},{"type":"Q","begin":{"x":1691,"y":1208},"end":{"x":1670,"y":1215}},{"type":"L","x":1640,"y":1224},{"type":"Q","begin":{"x":1636,"y":1226},"end":{"x":1559,"y":1263}},{"type":"L","x":1392,"y":1348},{"type":"Q","begin":{"x":1336.5,"y":1363.5},"end":{"x":1367,"y":1327}}],"track":[{"x":1635,"y":1128,"size":125},{"x":1371,"y":1344,"size":95}]},{"outline":[{"type":"M","x":1392,"y":1348},{"type":"Q","begin":{"x":1427,"y":1377},"end":{"x":1470,"y":1412.5}},{"type":"Q","begin":{"x":1513,"y":1448},"end":{"x":1536,"y":1466.5}},{"type":"Q","begin":{"x":1559,"y":1485},"end":{"x":1607.5,"y":1515}},{"type":"Q","begin":{"x":1656,"y":1545},"end":{"x":1725.5,"y":1578}},{"type":"Q","begin":{"x":1795,"y":1611},"end":{"x":1839.5,"y":1625.5}},{"type":"Q","begin":{"x":1884,"y":1640},"end":{"x":1907,"y":1646}},{"type":"L","x":1935,"y":1654},{"type":"Q","begin":{"x":1960,"y":1662},"end":{"x":1962.5,"y":1673}},{"type":"Q","begin":{"x":1965,"y":1684},"end":{"x":1946,"y":1690}},{"type":"L","x":1912,"y":1702},{"type":"Q","begin":{"x":1897,"y":1708},"end":{"x":1868,"y":1713.5}},{"type":"Q","begin":{"x":1839,"y":1719},"end":{"x":1826,"y":1721}},{"type":"L","x":1751,"y":1732},{"type":"Q","begin":{"x":1718,"y":1738},"end":{"x":1704,"y":1735}},{"type":"Q","begin":{"x":1685,"y":1733},"end":{"x":1656.5,"y":1715.5}},{"type":"Q","begin":{"x":1628,"y":1698},"end":{"x":1587,"y":1654}},{"type":"L","x":1498,"y":1558},{"type":"L","x":1420,"y":1477},{"type":"L","x":1326,"y":1372},{"type":"L","x":1275,"y":1328},{"type":"L","x":1281,"y":1266},{"type":"L","x":1367,"y":1327},{"type":"L","x":1392,"y":1348}],"track":[{"x":1292,"y":1302,"size":110},{"x":1698,"y":1648},{"x":1947,"y":1675,"size":100}]}]