[{"outline":[{"type":"M","x":676,"y":336},{"type":"Q","begin":{"x":667,"y":305},"end":{"x":661.5,"y":290}},{"type":"Q","begin":{"x":656,"y":275},"end":{"x":642.5,"y":242}},{"type":"Q","begin":{"x":629,"y":209},"end":{"x":617.5,"y":191.5}},{"type":"Q","begin":{"x":606,"y":174},"end":{"x":601,"y":162}},{"type":"Q","begin":{"x":596,"y":150},"end":{"x":603,"y":140.5}},{"type":"Q","begin":{"x":610,"y":131},"end":{"x":629,"y":128}},{"type":"Q","begin":{"x":647,"y":126},"end":{"x":676.5,"y":131.5}},{"type":"Q","begin":{"x":706,"y":137},"end":{"x":717.5,"y":140.5}},{"type":"Q","begin":{"x":729,"y":144},"end":{"x":743.5,"y":150.5}},{"type":"Q","begin":{"x":758,"y":157},"end":{"x":763.5,"y":162.5}},{"type":"Q","begin":{"x":769,"y":168},"end":{"x":772,"y":177}},{"type":"L","x":769,"y":216},{"type":"L","x":770,"y":317},{"type":"L","x":779,"y":381},{"type":"L","x":789,"y":475},{"type":"Q","begin":{"x":791,"y":498},"end":{"x":787.5,"y":514}},{"type":"Q","begin":{"x":784,"y":530},"end":{"x":772,"y":533.5}},{"type":"Q","begin":{"x":760,"y":537},"end":{"x":749,"y":526}},{"type":"Q","begin":{"x":738,"y":515},"end":{"x":727,"y":483}},{"type":"L","x":698,"y":402},{"type":"L","x":676,"y":336}],"track":[{"x":673,"y":136},{"x":766,"y":516}]},{"outline":[{"type":"M","x":698,"y":402},{"type":"L","x":587,"y":438},{"type":"Q","begin":{"x":531,"y":456},"end":{"x":521.5,"y":460}},{"type":"Q","begin":{"x":512,"y":464},"end":{"x":496.5,"y":472.5}},{"type":"Q","begin":{"x":481,"y":481},"end":{"x":476,"y":481}},{"type":"Q","begin":{"x":468,"y":483},"end":{"x":449,"y":475.5}},{"type":"Q","begin":{"x":430,"y":468},"end":{"x":415.5,"y":455}},{"type":"Q","begin":{"x":401,"y":442},"end":{"x":382.5,"y":420.5}},{"type":"Q","begin":{"x":364,"y":399},"end":{"x":357,"y":386.5}},{"type":"Q","begin":{"x":350,"y":374},"end":{"x":353,"y":364}},{"type":"Q","begin":{"x":354,"y":359},"end":{"x":358,"y":355}},{"type":"Q","begin":{"x":362,"y":351},"end":{"x":375,"y":352}},{"type":"L","x":401,"y":357},{"type":"Q","begin":{"x":407,"y":359},"end":{"x":432,"y":361}},{"type":"Q","begin":{"x":457,"y":363},"end":{"x":468.5,"y":363.5}},{"type":"Q","begin":{"x":480,"y":364},"end":{"x":525,"y":357}},{"type":"L","x":676,"y":336},{"type":"L","x":770,"y":317},{"type":"L","x":921,"y":301},{"type":"Q","begin":{"x":945,"y":299},"end":{"x":949,"y":316.5}},{"type":"Q","begin":{"x":953,"y":334},"end":{"x":930,"y":340}},{"type":"L","x":779,"y":381},{"type":"L","x":698,"y":402}],"track":[{"x":400,"y":420},{"x":940,"y":316}]},{"outline":[{"type":"M","x":1325,"y":254},{"type":"L","x":1439,"y":232},{"type":"L","x":1511,"y":216},{"type":"Q","begin":{"x":1526,"y":216},"end":{"x":1545,"y":221}},{"type":"Q","begin":{"x":1564,"y":226},"end":{"x":1588.5,"y":237.5}},{"type":"Q","begin":{"x":1613,"y":249},"end":{"x":1624,"y":259.5}},{"type":"Q","begin":{"x":1635,"y":270},"end":{"x":1635,"y":280}},{"type":"Q","begin":{"x":1633,"y":292},"end":{"x":1622.5,"y":298}},{"type":"Q","begin":{"x":1612,"y":304},"end":{"x":1600,"y":305.5}},{"type":"Q","begin":{"x":1588,"y":307},"end":{"x":1567,"y":308}},{"type":"L","x":1514,"y":312},{"type":"L","x":1389,"y":321},{"type":"L","x":1295,"y":329},{"type":"L","x":1200,"y":344},{"type":"L","x":1158,"y":353},{"type":"L","x":1115,"y":363},{"type":"Q","begin":{"x":1104,"y":363},"end":{"x":1093.5,"y":359.5}},{"type":"Q","begin":{"x":1083,"y":356},"end":{"x":1071.5,"y":350}},{"type":"Q","begin":{"x":1060,"y":344},"end":{"x":1048,"y":337.5}},{"type":"Q","begin":{"x":1036,"y":331},"end":{"x":1025.5,"y":320}},{"type":"Q","begin":{"x":1015,"y":309},"end":{"x":1018.5,"y":301}},{"type":"Q","begin":{"x":1022,"y":293},"end":{"x":1042,"y":292}},{"type":"L","x":1074,"y":291},{"type":"Q","begin":{"x":1092,"y":291},"end":{"x":1157,"y":282}},{"type":"L","x":1217,"y":274},{"type":"L","x":1325,"y":254}],"track":[{"x":1066,"y":340},{"x":1580,"y":246}]},{"outline":[{"type":"M","x":1217,"y":274},{"type":"Q","begin":{"x":1220,"y":255},"end":{"x":1222,"y":245}},{"type":"L","x":1227,"y":207},{"type":"Q","begin":{"x":1232,"y":167},"end":{"x":1233,"y":158}},{"type":"Q","begin":{"x":1234,"y":132},"end":{"x":1229.5,"y":110}},{"type":"Q","begin":{"x":1225,"y":88},"end":{"x":1227.5,"y":77}},{"type":"Q","begin":{"x":1230,"y":66},"end":{"x":1242,"y":60.5}},{"type":"Q","begin":{"x":1254,"y":55},"end":{"x":1282,"y":66}},{"type":"Q","begin":{"x":1315,"y":80},"end":{"x":1332.5,"y":90}},{"type":"Q","begin":{"x":1350,"y":100},"end":{"x":1369.5,"y":118.5}},{"type":"Q","begin":{"x":1389,"y":137},"end":{"x":1389,"y":151}},{"type":"Q","begin":{"x":1388,"y":160},"end":{"x":1383.5,"y":167}},{"type":"Q","begin":{"x":1379,"y":174},"end":{"x":1369,"y":189}},{"type":"L","x":1355,"y":210},{"type":"L","x":1325,"y":254},{"type":"L","x":1295,"y":329},{"type":"Q","begin":{"x":1277,"y":356},"end":{"x":1262.5,"y":378.5}},{"type":"Q","begin":{"x":1248,"y":401},"end":{"x":1233.5,"y":425}},{"type":"Q","begin":{"x":1219,"y":449},"end":{"x":1210,"y":459}},{"type":"L","x":1191,"y":481},{"type":"Q","begin":{"x":1177,"y":498},"end":{"x":1168,"y":493}},{"type":"Q","begin":{"x":1159,"y":488},"end":{"x":1165,"y":467}},{"type":"L","x":1173,"y":436},{"type":"L","x":1186,"y":392},{"type":"L","x":1200,"y":344},{"type":"L","x":1217,"y":274}],"track":[{"x":1290,"y":76},{"x":1316,"y":146},{"x":1180,"y":480}]},{"outline":[{"type":"M","x":1059,"y":545},{"type":"Q","begin":{"x":1097,"y":542},"end":{"x":1110,"y":539.5}},{"type":"Q","begin":{"x":1123,"y":537},"end":{"x":1148,"y":532.5}},{"type":"Q","begin":{"x":1173,"y":528},"end":{"x":1204,"y":522}},{"type":"Q","begin":{"x":1235,"y":516},"end":{"x":1252,"y":512}},{"type":"L","x":1293,"y":501},{"type":"Q","begin":{"x":1314,"y":496},"end":{"x":1327,"y":496}},{"type":"Q","begin":{"x":1340,"y":497},"end":{"x":1357,"y":504}},{"type":"Q","begin":{"x":1374,"y":511},"end":{"x":1400,"y":523.5}},{"type":"Q","begin":{"x":1426,"y":536},"end":{"x":1437.5,"y":544.5}},{"type":"Q","begin":{"x":1449,"y":553},"end":{"x":1457,"y":562}},{"type":"Q","begin":{"x":1465,"y":571},"end":{"x":1465.5,"y":576.5}},{"type":"Q","begin":{"x":1466,"y":582},"end":{"x":1459,"y":592}},{"type":"Q","begin":{"x":1447,"y":610},"end":{"x":1439.5,"y":621.5}},{"type":"Q","begin":{"x":1432,"y":633},"end":{"x":1429,"y":646}},{"type":"L","x":1421,"y":672},{"type":"L","x":1399,"y":745},{"type":"L","x":1354,"y":873},{"type":"Q","begin":{"x":1223,"y":931.5},"end":{"x":1258,"y":842}},{"type":"L","x":1283,"y":755},{"type":"L","x":1295,"y":685},{"type":"L","x":1301,"y":645},{"type":"Q","begin":{"x":1302,"y":637},"end":{"x":1302.5,"y":626}},{"type":"Q","begin":{"x":1303,"y":615},"end":{"x":1302,"y":611}},{"type":"Q","begin":{"x":1299,"y":605},"end":{"x":1291,"y":601}},{"type":"Q","begin":{"x":1283,"y":597},"end":{"x":1272,"y":595.5}},{"type":"Q","begin":{"x":1261,"y":594},"end":{"x":1251,"y":593}},{"type":"Q","begin":{"x":1232,"y":593},"end":{"x":1189,"y":599}},{"type":"Q","begin":{"x":1146,"y":605},"end":{"x":1108,"y":608}},{"type":"L","x":1052,"y":613},{"type":"L","x":949,"y":625},{"type":"Q","begin":{"x":899,"y":631},"end":{"x":874,"y":633}},{"type":"L","x":799,"y":640},{"type":"Q","begin":{"x":756,"y":645},"end":{"x":729,"y":646.5}},{"type":"Q","begin":{"x":702,"y":648},"end":{"x":682.5,"y":650.5}},{"type":"Q","begin":{"x":663,"y":653},"end":{"x":659,"y":652}},{"type":"Q","begin":{"x":647,"y":652},"end":{"x":634.5,"y":649}},{"type":"Q","begin":{"x":622,"y":646},"end":{"x":608.5,"y":639.5}},{"type":"Q","begin":{"x":595,"y":633},"end":{"x":584.5,"y":624}},{"type":"Q","begin":{"x":574,"y":615},"end":{"x":575.5,"y":607}},{"type":"Q","begin":{"x":577,"y":599},"end":{"x":598,"y":596}},{"type":"L","x":629,"y":592},{"type":"Q","begin":{"x":633,"y":592},"end":{"x":685.5,"y":589}},{"type":"Q","begin":{"x":738,"y":586},"end":{"x":815,"y":576}},{"type":"L","x":907,"y":565},{"type":"L","x":946,"y":560},{"type":"L","x":1059,"y":545}],"track":[{"x":606,"y":623},{"x":890,"y":596},{"x":1320,"y":550},{"x":1436,"y":576},{"x":1363,"y":613},{"x":1280,"y":880}]},{"outline":[{"type":"M","x":1421,"y":672},{"type":"Q","begin":{"x":1457,"y":666},"end":{"x":1476,"y":663}},{"type":"Q","begin":{"x":1495,"y":660},"end":{"x":1546,"y":653}},{"type":"Q","begin":{"x":1597,"y":646},"end":{"x":1638.5,"y":639.5}},{"type":"Q","begin":{"x":1680,"y":633},"end":{"x":1703,"y":634}},{"type":"Q","begin":{"x":1726,"y":636},"end":{"x":1752,"y":644}},{"type":"Q","begin":{"x":1778,"y":652},"end":{"x":1796.5,"y":663}},{"type":"Q","begin":{"x":1815,"y":674},"end":{"x":1828.5,"y":687.5}},{"type":"Q","begin":{"x":1842,"y":701},"end":{"x":1841,"y":708}},{"type":"Q","begin":{"x":1839,"y":715},"end":{"x":1827.5,"y":721}},{"type":"Q","begin":{"x":1816,"y":727},"end":{"x":1792,"y":728}},{"type":"L","x":1399,"y":745},{"type":"L","x":1283,"y":755},{"type":"L","x":1049,"y":773},{"type":"L","x":948,"y":784},{"type":"Q","begin":{"x":870,"y":792},"end":{"x":830,"y":796.5}},{"type":"Q","begin":{"x":790,"y":801},"end":{"x":698,"y":812.5}},{"type":"Q","begin":{"x":606,"y":824},"end":{"x":562.5,"y":830}},{"type":"Q","begin":{"x":519,"y":836},"end":{"x":471.5,"y":844}},{"type":"Q","begin":{"x":424,"y":852},"end":{"x":389,"y":860}},{"type":"Q","begin":{"x":354,"y":868},"end":{"x":340,"y":868}},{"type":"Q","begin":{"x":323,"y":869},"end":{"x":304,"y":865.5}},{"type":"Q","begin":{"x":285,"y":862},"end":{"x":260,"y":853}},{"type":"Q","begin":{"x":235,"y":844},"end":{"x":220,"y":832}},{"type":"Q","begin":{"x":205,"y":820},"end":{"x":207.5,"y":809}},{"type":"Q","begin":{"x":210,"y":798},"end":{"x":229,"y":796}},{"type":"L","x":261,"y":793},{"type":"Q","begin":{"x":351,"y":785},"end":{"x":379,"y":782}},{"type":"L","x":532,"y":768},{"type":"Q","begin":{"x":589,"y":763},"end":{"x":709.5,"y":750.5}},{"type":"Q","begin":{"x":830,"y":738},"end":{"x":887,"y":731}},{"type":"L","x":948,"y":724},{"type":"L","x":1050,"y":713},{"type":"L","x":1295,"y":685},{"type":"L","x":1421,"y":672}],"track":[{"x":253,"y":843},{"x":520,"y":793},{"x":1026,"y":743},{"x":1800,"y":676}]},{"outline":[{"type":"M","x":1354,"y":873},{"type":"L","x":1369,"y":889},{"type":"Q","begin":{"x":1376,"y":898},"end":{"x":1375,"y":905}},{"type":"Q","begin":{"x":1374,"y":912},"end":{"x":1358.5,"y":916.5}},{"type":"Q","begin":{"x":1343,"y":921},"end":{"x":1328.5,"y":922}},{"type":"Q","begin":{"x":1314,"y":923},"end":{"x":1267,"y":925.5}},{"type":"Q","begin":{"x":1220,"y":928},"end":{"x":1159.5,"y":930.5}},{"type":"Q","begin":{"x":1099,"y":933},"end":{"x":1081,"y":934}},{"type":"L","x":1047,"y":937},{"type":"L","x":944,"y":946},{"type":"Q","begin":{"x":916,"y":951},"end":{"x":902,"y":952}},{"type":"L","x":828,"y":962},{"type":"Q","begin":{"x":778,"y":969},"end":{"x":740,"y":976.5}},{"type":"Q","begin":{"x":702,"y":984},"end":{"x":687,"y":984}},{"type":"Q","begin":{"x":667,"y":985},"end":{"x":646,"y":981.5}},{"type":"Q","begin":{"x":625,"y":978},"end":{"x":611.5,"y":972.5}},{"type":"Q","begin":{"x":598,"y":967},"end":{"x":583.5,"y":957}},{"type":"Q","begin":{"x":569,"y":947},"end":{"x":570,"y":939.5}},{"type":"Q","begin":{"x":571,"y":932},"end":{"x":591,"y":930}},{"type":"L","x":619,"y":928},{"type":"Q","begin":{"x":643,"y":927},"end":{"x":687,"y":921}},{"type":"L","x":768,"y":911},{"type":"Q","begin":{"x":857,"y":901},"end":{"x":858,"y":900}},{"type":"L","x":947,"y":888},{"type":"L","x":1049,"y":874},{"type":"Q","begin":{"x":1077,"y":871},"end":{"x":1103,"y":867}},{"type":"Q","begin":{"x":1129,"y":863},"end":{"x":1173.5,"y":855.5}},{"type":"Q","begin":{"x":1218,"y":848},"end":{"x":1219,"y":847}},{"type":"L","x":1258,"y":842},{"type":"L","x":1354,"y":873}],"track":[{"x":633,"y":963},{"x":873,"y":933},{"x":1330,"y":863}]},{"outline":[{"type":"M","x":946,"y":560},{"type":"Q","begin":{"x":941,"y":528},"end":{"x":938,"y":507}},{"type":"Q","begin":{"x":935,"y":486},"end":{"x":930,"y":473}},{"type":"L","x":915,"y":440},{"type":"Q","begin":{"x":909,"y":422},"end":{"x":914.5,"y":414.5}},{"type":"Q","begin":{"x":920,"y":407},"end":{"x":942,"y":406}},{"type":"Q","begin":{"x":959,"y":406},"end":{"x":976,"y":410}},{"type":"Q","begin":{"x":993,"y":414},"end":{"x":1014,"y":421.5}},{"type":"Q","begin":{"x":1035,"y":429},"end":{"x":1051,"y":437.5}},{"type":"Q","begin":{"x":1067,"y":446},"end":{"x":1075.5,"y":457.5}},{"type":"Q","begin":{"x":1084,"y":469},"end":{"x":1082,"y":479}},{"type":"L","x":1073,"y":496},{"type":"L","x":1066,"y":520},{"type":"L","x":1059,"y":545},{"type":"L","x":1052,"y":613},{"type":"L","x":1050,"y":713},{"type":"L","x":1049,"y":773},{"type":"L","x":1049,"y":874},{"type":"L","x":1047,"y":937},{"type":"L","x":1043,"y":1340},{"type":"L","x":1040,"y":1415},{"type":"L","x":1033,"y":1751},{"type":"Q","begin":{"x":1032,"y":1789},"end":{"x":1029,"y":1826}},{"type":"Q","begin":{"x":1026,"y":1863},"end":{"x":1018.5,"y":1891.5}},{"type":"Q","begin":{"x":1011,"y":1920},"end":{"x":995.5,"y":1940.5}},{"type":"Q","begin":{"x":980,"y":1961},"end":{"x":969,"y":1960}},{"type":"Q","begin":{"x":957,"y":1960},"end":{"x":943,"y":1939.5}},{"type":"Q","begin":{"x":929,"y":1919},"end":{"x":921,"y":1898}},{"type":"Q","begin":{"x":913,"y":1877},"end":{"x":905,"y":1846.5}},{"type":"Q","begin":{"x":897,"y":1816},"end":{"x":899,"y":1801}},{"type":"Q","begin":{"x":899,"y":1794},"end":{"x":908.5,"y":1764.5}},{"type":"Q","begin":{"x":918,"y":1735},"end":{"x":924,"y":1691}},{"type":"Q","begin":{"x":930,"y":1647},"end":{"x":934,"y":1608.5}},{"type":"Q","begin":{"x":938,"y":1570},"end":{"x":939,"y":1548}},{"type":"L","x":942,"y":1426},{"type":"L","x":941,"y":1348},{"type":"L","x":944,"y":946},{"type":"L","x":947,"y":888},{"type":"L","x":948,"y":784},{"type":"L","x":948,"y":724},{"type":"L","x":949,"y":625},{"type":"L","x":946,"y":560}],"track":[{"x":916,"y":403},{"x":996,"y":493},{"x":1000,"y":896},{"x":1000,"y":1200},{"x":973,"y":1933}]},{"outline":[{"type":"M","x":546,"y":1462},{"type":"Q","begin":{"x":540,"y":1511},"end":{"x":539,"y":1520}},{"type":"L","x":530,"y":1573},{"type":"L","x":514,"y":1633},{"type":"Q","begin":{"x":497,"y":1675},"end":{"x":477,"y":1718}},{"type":"Q","begin":{"x":457,"y":1761},"end":{"x":418,"y":1801.5}},{"type":"Q","begin":{"x":379,"y":1842},"end":{"x":332,"y":1875}},{"type":"L","x":299,"y":1898},{"type":"Q","begin":{"x":274,"y":1916},"end":{"x":268.5,"y":1910.5}},{"type":"Q","begin":{"x":263,"y":1905},"end":{"x":263.5,"y":1898.5}},{"type":"Q","begin":{"x":264,"y":1892},"end":{"x":279,"y":1875}},{"type":"L","x":305,"y":1845},{"type":"Q","begin":{"x":327,"y":1820},"end":{"x":356.5,"y":1772}},{"type":"Q","begin":{"x":386,"y":1724},"end":{"x":405.5,"y":1673.5}},{"type":"Q","begin":{"x":425,"y":1623},"end":{"x":436,"y":1564}},{"type":"Q","begin":{"x":447,"y":1505},"end":{"x":455.5,"y":1431}},{"type":"Q","begin":{"x":464,"y":1357},"end":{"x":465.5,"y":1324.5}},{"type":"Q","begin":{"x":467,"y":1292},"end":{"x":467,"y":1208}},{"type":"Q","begin":{"x":466,"y":1159},"end":{"x":462.5,"y":1137}},{"type":"Q","begin":{"x":459,"y":1115},"end":{"x":449.5,"y":1092}},{"type":"Q","begin":{"x":440,"y":1069},"end":{"x":431,"y":1058}},{"type":"L","x":406,"y":1030},{"type":"Q","begin":{"x":399,"y":1017},"end":{"x":403.5,"y":1009.5}},{"type":"Q","begin":{"x":408,"y":1002},"end":{"x":425,"y":1000}},{"type":"Q","begin":{"x":442,"y":999},"end":{"x":467.5,"y":1004.5}},{"type":"Q","begin":{"x":493,"y":1010},"end":{"x":521.5,"y":1018.5}},{"type":"Q","begin":{"x":550,"y":1027},"end":{"x":563.5,"y":1038.5}},{"type":"Q","begin":{"x":577,"y":1050},"end":{"x":578.5,"y":1057.5}},{"type":"Q","begin":{"x":580,"y":1065},"end":{"x":574,"y":1087}},{"type":"Q","begin":{"x":570,"y":1100},"end":{"x":569,"y":1121}},{"type":"L","x":566,"y":1190},{"type":"L","x":564,"y":1232},{"type":"L","x":561,"y":1290},{"type":"Q","begin":{"x":558,"y":1339},"end":{"x":557,"y":1351}},{"type":"L","x":553,"y":1388},{"type":"L","x":546,"y":1462}],"track":[{"x":443,"y":1013},{"x":510,"y":1133},{"x":493,"y":1593},{"x":283,"y":1896}]},{"outline":[{"type":"M","x":564,"y":1232},{"type":"L","x":679,"y":1225},{"type":"Q","begin":{"x":691,"y":1225},"end":{"x":703,"y":1221.5}},{"type":"Q","begin":{"x":715,"y":1218},"end":{"x":718,"y":1213.5}},{"type":"Q","begin":{"x":721,"y":1209},"end":{"x":722,"y":1195.5}},{"type":"Q","begin":{"x":723,"y":1182},"end":{"x":723,"y":1179}},{"type":"L","x":719,"y":1097},{"type":"L","x":715,"y":1064},{"type":"Q","begin":{"x":713,"y":1045},"end":{"x":711,"y":1040}},{"type":"L","x":702,"y":1024},{"type":"Q","begin":{"x":697,"y":1014},"end":{"x":701,"y":1009}},{"type":"Q","begin":{"x":705,"y":1004},"end":{"x":716,"y":1003}},{"type":"Q","begin":{"x":731,"y":1002},"end":{"x":752.5,"y":1007.5}},{"type":"Q","begin":{"x":774,"y":1013},"end":{"x":791,"y":1020}},{"type":"Q","begin":{"x":808,"y":1027},"end":{"x":821,"y":1038}},{"type":"Q","begin":{"x":834,"y":1049},"end":{"x":834,"y":1058}},{"type":"Q","begin":{"x":833,"y":1061},"end":{"x":828,"y":1071}},{"type":"Q","begin":{"x":823,"y":1081},"end":{"x":816,"y":1102.5}},{"type":"Q","begin":{"x":809,"y":1124},"end":{"x":809,"y":1132}},{"type":"L","x":802,"y":1196},{"type":"Q","begin":{"x":799,"y":1222},"end":{"x":798.5,"y":1235.5}},{"type":"Q","begin":{"x":798,"y":1249},"end":{"x":794.5,"y":1257}},{"type":"Q","begin":{"x":791,"y":1265},"end":{"x":781,"y":1270}},{"type":"Q","begin":{"x":771,"y":1275},"end":{"x":751,"y":1278.5}},{"type":"Q","begin":{"x":731,"y":1282},"end":{"x":721,"y":1282}},{"type":"L","x":561,"y":1290},{"type":"Q","begin":{"x":505.5,"y":1241},"end":{"x":564,"y":1232}}],"track":[{"x":766,"y":1023},{"x":763,"y":1230},{"x":546,"y":1260}]},{"outline":[{"type":"M","x":1452,"y":1160},{"type":"L","x":1359,"y":1182},{"type":"Q","begin":{"x":1323,"y":1191},"end":{"x":1304,"y":1199}},{"type":"L","x":1270,"y":1216},{"type":"Q","begin":{"x":1245,"y":1229},"end":{"x":1234,"y":1239}},{"type":"Q","begin":{"x":1223,"y":1249},"end":{"x":1216.5,"y":1251}},{"type":"Q","begin":{"x":1210,"y":1253},"end":{"x":1201,"y":1246}},{"type":"Q","begin":{"x":1192,"y":1241},"end":{"x":1182,"y":1218}},{"type":"L","x":1167,"y":1188},{"type":"Q","begin":{"x":1158,"y":1172},"end":{"x":1159,"y":1162}},{"type":"Q","begin":{"x":1159,"y":1159},"end":{"x":1168.5,"y":1138.5}},{"type":"Q","begin":{"x":1178,"y":1118},"end":{"x":1181,"y":1097.5}},{"type":"Q","begin":{"x":1184,"y":1077},"end":{"x":1185.5,"y":1052.5}},{"type":"Q","begin":{"x":1187,"y":1028},"end":{"x":1182,"y":1011}},{"type":"L","x":1173,"y":989},{"type":"Q","begin":{"x":1169,"y":979},"end":{"x":1171.5,"y":972.5}},{"type":"Q","begin":{"x":1174,"y":966},"end":{"x":1184,"y":962}},{"type":"Q","begin":{"x":1194,"y":958},"end":{"x":1220,"y":969}},{"type":"L","x":1261,"y":987},{"type":"Q","begin":{"x":1276,"y":996},"end":{"x":1287,"y":1005.5}},{"type":"Q","begin":{"x":1298,"y":1015},"end":{"x":1298.5,"y":1020}},{"type":"Q","begin":{"x":1299,"y":1025},"end":{"x":1295,"y":1032}},{"type":"Q","begin":{"x":1284,"y":1051},"end":{"x":1281.5,"y":1056.5}},{"type":"Q","begin":{"x":1279,"y":1062},"end":{"x":1275.5,"y":1081.5}},{"type":"Q","begin":{"x":1272,"y":1101},"end":{"x":1273,"y":1105}},{"type":"L","x":1276,"y":1132},{"type":"L","x":1452,"y":1114},{"type":"Q","begin":{"x":1565,"y":1110},"end":{"x":1452,"y":1160}}],"track":[{"x":1243,"y":990},{"x":1210,"y":1136},{"x":1180,"y":1203},{"x":1260,"y":1180},{"x":1486,"y":1126}]},{"outline":[{"type":"M","x":1448,"y":1317},{"type":"L","x":1452,"y":1160},{"type":"L","x":1452,"y":1114},{"type":"Q","begin":{"x":1450,"y":1089},"end":{"x":1449,"y":1070.5}},{"type":"Q","begin":{"x":1448,"y":1052},"end":{"x":1443.5,"y":1029.5}},{"type":"Q","begin":{"x":1439,"y":1007},"end":{"x":1433.5,"y":993}},{"type":"Q","begin":{"x":1428,"y":979},"end":{"x":1419,"y":957}},{"type":"Q","begin":{"x":1410,"y":935},"end":{"x":1413.5,"y":927}},{"type":"Q","begin":{"x":1417,"y":919},"end":{"x":1433,"y":915}},{"type":"Q","begin":{"x":1446,"y":912},"end":{"x":1471,"y":919}},{"type":"Q","begin":{"x":1496,"y":926},"end":{"x":1519,"y":935}},{"type":"Q","begin":{"x":1542,"y":944},"end":{"x":1560,"y":962}},{"type":"Q","begin":{"x":1578,"y":980},"end":{"x":1578,"y":996}},{"type":"Q","begin":{"x":1577,"y":1003},"end":{"x":1567.5,"y":1026}},{"type":"Q","begin":{"x":1558,"y":1049},"end":{"x":1554.5,"y":1086.5}},{"type":"Q","begin":{"x":1551,"y":1124},"end":{"x":1550,"y":1177}},{"type":"L","x":1536,"y":1780},{"type":"Q","begin":{"x":1535,"y":1819},"end":{"x":1532,"y":1855}},{"type":"Q","begin":{"x":1529,"y":1891},"end":{"x":1521.5,"y":1919.5}},{"type":"Q","begin":{"x":1514,"y":1948},"end":{"x":1498.5,"y":1968.5}},{"type":"Q","begin":{"x":1483,"y":1989},"end":{"x":1472,"y":1988}},{"type":"Q","begin":{"x":1460,"y":1988},"end":{"x":1446,"y":1968}},{"type":"Q","begin":{"x":1432,"y":1948},"end":{"x":1423.5,"y":1924.5}},{"type":"Q","begin":{"x":1415,"y":1901},"end":{"x":1408,"y":1873}},{"type":"Q","begin":{"x":1401,"y":1845},"end":{"x":1403,"y":1829}},{"type":"Q","begin":{"x":1403,"y":1820},"end":{"x":1412,"y":1790.5}},{"type":"Q","begin":{"x":1421,"y":1761},"end":{"x":1425.5,"y":1730.5}},{"type":"Q","begin":{"x":1430,"y":1700},"end":{"x":1435,"y":1654}},{"type":"Q","begin":{"x":1440,"y":1608},"end":{"x":1441,"y":1602}},{"type":"L","x":1442,"y":1577},{"type":"L","x":1443,"y":1512},{"type":"L","x":1446,"y":1397},{"type":"L","x":1448,"y":1317}],"track":[{"x":1483,"y":936},{"x":1506,"y":1036},{"x":1480,"y":1966}]},{"outline":[{"type":"M","x":1043,"y":1340},{"type":"Q","begin":{"x":1080,"y":1335},"end":{"x":1113,"y":1330.5}},{"type":"Q","begin":{"x":1146,"y":1326},"end":{"x":1151,"y":1325}},{"type":"L","x":1216,"y":1314},{"type":"Q","begin":{"x":1269,"y":1306},"end":{"x":1298,"y":1296.5}},{"type":"Q","begin":{"x":1327,"y":1287},"end":{"x":1338,"y":1286}},{"type":"Q","begin":{"x":1349,"y":1285},"end":{"x":1367.5,"y":1289.5}},{"type":"Q","begin":{"x":1386,"y":1294},"end":{"x":1399,"y":1298}},{"type":"Q","begin":{"x":1412,"y":1302},"end":{"x":1420,"y":1305}},{"type":"L","x":1448,"y":1317},{"type":"L","x":1446,"y":1397},{"type":"Q","begin":{"x":1422,"y":1400},"end":{"x":1412.5,"y":1400.5}},{"type":"Q","begin":{"x":1403,"y":1401},"end":{"x":1351,"y":1402}},{"type":"L","x":1247,"y":1407},{"type":"L","x":1097,"y":1412},{"type":"Q","begin":{"x":1066,"y":1414},"end":{"x":1054,"y":1414}},{"type":"L","x":1040,"y":1415},{"type":"L","x":942,"y":1426},{"type":"Q","begin":{"x":910,"y":1431},"end":{"x":895,"y":1432}},{"type":"L","x":850,"y":1436},{"type":"Q","begin":{"x":820,"y":1439},"end":{"x":799,"y":1442}},{"type":"L","x":719,"y":1457},{"type":"L","x":671,"y":1465},{"type":"Q","begin":{"x":631,"y":1473},"end":{"x":609,"y":1474.5}},{"type":"Q","begin":{"x":587,"y":1476},"end":{"x":565,"y":1468}},{"type":"L","x":546,"y":1462},{"type":"L","x":553,"y":1388},{"type":"Q","begin":{"x":600,"y":1384},"end":{"x":624,"y":1381}},{"type":"L","x":722,"y":1373},{"type":"Q","begin":{"x":761,"y":1370},"end":{"x":813,"y":1363}},{"type":"L","x":877,"y":1355},{"type":"L","x":941,"y":1348},{"type":"L","x":1043,"y":1340}],"track":[{"x":553,"y":1423},{"x":820,"y":1413},{"x":1460,"y":1356}]},{"outline":[{"type":"M","x":530,"y":1573},{"type":"Q","begin":{"x":561,"y":1571},"end":{"x":581.5,"y":1568}},{"type":"Q","begin":{"x":602,"y":1565},"end":{"x":628,"y":1557}},{"type":"L","x":678,"y":1542},{"type":"Q","begin":{"x":712,"y":1533},"end":{"x":727,"y":1526.5}},{"type":"Q","begin":{"x":742,"y":1520},"end":{"x":749,"y":1520}},{"type":"Q","begin":{"x":757,"y":1521},"end":{"x":769,"y":1527}},{"type":"Q","begin":{"x":781,"y":1533},"end":{"x":794.5,"y":1543}},{"type":"Q","begin":{"x":808,"y":1553},"end":{"x":815,"y":1561}},{"type":"L","x":826,"y":1577},{"type":"Q","begin":{"x":830,"y":1585},"end":{"x":830.5,"y":1588.5}},{"type":"Q","begin":{"x":831,"y":1592},"end":{"x":824,"y":1598}},{"type":"L","x":811,"y":1609},{"type":"Q","begin":{"x":805,"y":1615},"end":{"x":801,"y":1626.5}},{"type":"Q","begin":{"x":797,"y":1638},"end":{"x":795,"y":1656}},{"type":"L","x":791,"y":1694},{"type":"L","x":775,"y":1829},{"type":"Q","begin":{"x":773,"y":1846},"end":{"x":764,"y":1867}},{"type":"Q","begin":{"x":755,"y":1888},"end":{"x":745.5,"y":1895.5}},{"type":"Q","begin":{"x":736,"y":1903},"end":{"x":728,"y":1901}},{"type":"Q","begin":{"x":722,"y":1901},"end":{"x":716.5,"y":1895.5}},{"type":"Q","begin":{"x":711,"y":1890},"end":{"x":702,"y":1868}},{"type":"L","x":687,"y":1835},{"type":"Q","begin":{"x":680,"y":1818},"end":{"x":682,"y":1799}},{"type":"Q","begin":{"x":682,"y":1788},"end":{"x":688,"y":1764.5}},{"type":"Q","begin":{"x":694,"y":1741},"end":{"x":702,"y":1705}},{"type":"Q","begin":{"x":710,"y":1669},"end":{"x":710.5,"y":1652}},{"type":"Q","begin":{"x":711,"y":1635},"end":{"x":705,"y":1627}},{"type":"Q","begin":{"x":699,"y":1619},"end":{"x":681,"y":1616}},{"type":"Q","begin":{"x":671,"y":1615},"end":{"x":638,"y":1619}},{"type":"L","x":589,"y":1623},{"type":"L","x":547,"y":1629},{"type":"L","x":514,"y":1633},{"type":"L","x":530,"y":1573}],"track":[{"x":530,"y":1603},{"x":713,"y":1573},{"x":793,"y":1553},{"x":760,"y":1623},{"x":733,"y":1886}]},{"outline":[{"type":"M","x":1442,"y":1577},{"type":"Q","begin":{"x":1411,"y":1579},"end":{"x":1396,"y":1580}},{"type":"L","x":1337,"y":1585},{"type":"Q","begin":{"x":1304,"y":1588},"end":{"x":1283,"y":1589}},{"type":"L","x":1250,"y":1591},{"type":"Q","begin":{"x":1135.5,"y":1561},"end":{"x":1233,"y":1537}},{"type":"Q","begin":{"x":1295,"y":1522},"end":{"x":1327,"y":1513.5}},{"type":"Q","begin":{"x":1359,"y":1505},"end":{"x":1376,"y":1505}},{"type":"L","x":1412,"y":1509},{"type":"L","x":1443,"y":1512},{"type":"L","x":1442,"y":1577}],"track":[{"x":1235,"y":1563},{"x":1413,"y":1543}]},{"outline":[{"type":"M","x":1250,"y":1591},{"type":"L","x":1251,"y":1767},{"type":"Q","begin":{"x":1251,"y":1786},"end":{"x":1249.5,"y":1802.5}},{"type":"Q","begin":{"x":1248,"y":1819},"end":{"x":1243,"y":1839}},{"type":"Q","begin":{"x":1238,"y":1859},"end":{"x":1228.5,"y":1872}},{"type":"Q","begin":{"x":1219,"y":1885},"end":{"x":1212,"y":1885}},{"type":"Q","begin":{"x":1206,"y":1886},"end":{"x":1197,"y":1880}},{"type":"Q","begin":{"x":1188,"y":1874},"end":{"x":1180.5,"y":1862.5}},{"type":"Q","begin":{"x":1173,"y":1851},"end":{"x":1168.5,"y":1834.5}},{"type":"Q","begin":{"x":1164,"y":1818},"end":{"x":1165,"y":1805}},{"type":"L","x":1172,"y":1747},{"type":"L","x":1171,"y":1663},{"type":"Q","begin":{"x":1170,"y":1648},"end":{"x":1166.5,"y":1622.5}},{"type":"Q","begin":{"x":1163,"y":1597},"end":{"x":1159.5,"y":1587.5}},{"type":"Q","begin":{"x":1156,"y":1578},"end":{"x":1148,"y":1562}},{"type":"Q","begin":{"x":1140,"y":1546},"end":{"x":1141,"y":1537}},{"type":"Q","begin":{"x":1142,"y":1528},"end":{"x":1152.5,"y":1521}},{"type":"Q","begin":{"x":1163,"y":1514},"end":{"x":1176,"y":1519}},{"type":"L","x":1233,"y":1537},{"type":"L","x":1250,"y":1591}],"track":[{"x":1186,"y":1538},{"x":1211,"y":1846}]}]